{
    "團體類型": "社會團體",
    "團體分類": "學術文化團體",
    "團體名稱": "台灣兒童文學研究學會",
    "現任理事長": "戴絲美",
    "理事長屆次": "2",
    "理事長任期": "104-11-06",
    "成立日期": "101-07-20",
    "核准立案字號": "1010396811",
    "團體狀態": "已立案",
    "郵遞區號": "407",
    "會址": "臺中市西屯區臺灣大道四段1727號(東海大學外國語文學系)",
    "電話": "04-23590121轉31200~2",
    "傳真": "02-28817609",
    "電子郵件": "jmklassen@scu.edu.tw",
    "會員人數": "46",
    "會員代表人數": "0",
    "宗旨": "提倡台灣兒童文學研究風氣，並促進國內外兒童文學之學術交流。",
    "任務": "推動國內各大專院校之兒童文學研究合作。\r\n促進國際兒童文學研究與學術交流。\r\n舉辦兒童文學術研討會、讀書會與工作坊等等。",
    "全國性\/地區性": "全國性",
    "行政區": "臺中市"
}