{
    "團體類型": "社會團體",
    "團體分類": "學術文化團體",
    "團體名稱": "台灣新移民文化交流協會",
    "現任理事長": "鄧梅",
    "理事長屆次": "2",
    "理事長任期": "102-12-08",
    "成立日期": "100-12-31",
    "核准立案字號": "1010076065",
    "團體狀態": "解散",
    "郵遞區號": "235",
    "會址": "新北市中和區建康路130號8樓之9",
    "會員人數": "85",
    "會員代表人數": "0",
    "宗旨": "以促進台灣國國民與新移民之文化交流並增進彼此之了解為宗旨，",
    "任務": "一、推廣新移民文化之意識價值、社會認識，促進新移民母國文化融入在生活。\r\n二、與國內、外(國際合作)各種文化活動，向社會大眾推廣多元文化。\r\n三、結合移民文化之愛好者，舉辦新移民藝文活動，活絡新移民文化活動及交流。\r\n四、結合媒體傳播，發行刊物、形塑新移民文化氛圍，凝聚新移民文化能量。\r\n五、辦理相關新移民語文課程、兒童母語傳承、家庭親子教育、提高國人及新移民之文化概念。\r\n六、協助主管機關指導辦理有關職培訓，支擬新移嚴家庭生活能力。\r\n七、協助社會公益團體服務各項活動。\r\n八、其他與本會宗旨相關之事項。",
    "全國性\/地區性": "全國性",
    "行政區": "新北市"
}