{
    "團體類型": "社會團體",
    "團體分類": "社會服務及慈善團體",
    "團體名稱": "中華職能再造創業培訓推展協會",
    "現任理事長": "周培基",
    "理事長屆次": "1",
    "理事長任期": "104-04-12",
    "成立日期": "104-04-12",
    "核准立案字號": "1040042088",
    "團體狀態": "已立案",
    "郵遞區號": "220",
    "會址": "新北市板橋區民生路二段192號四樓",
    "電話": "02-22562052",
    "會員人數": "30",
    "會員代表人數": "0",
    "宗旨": "本會為依法設立、非以營利為目的之社會團體。\r\n宗旨如下:本會結合各界關懷專業人才,配合政府推動兩性平權,培養各項專技人才協助失業人士與退休人員學習技能與社會融合,提升文化和諧、安定為宗旨。",
    "任務": "一、結合社會資源,配合政府政策向政府申請補助經費,依相關規定舉辦各職類技藝證照培訓技能研習訓練、多元就業方案、國際文化研習營,減少失業率,以利二度就業。\r\n二、舉辦失業人員專職培訓,提升職場再度就業的信心。\r\n三、協助退休人員建立專長資料,媒合中小企業再度就業。\r\n四、加強會員第二專長培訓,以利二度就業。\r\n五、發行出版刊物,架設村里網站平台、提供社會相關資訊信息。\r\n六、協助各地區或縣市政府推行公益活動觀摩考察國際性會務事項。\r\n七、其他與章程所訂宗旨與任務相關事項。",
    "全國性\/地區性": "全國性",
    "行政區": "新北市"
}