{
    "團體類型": "社會團體",
    "團體分類": "學術文化團體",
    "團體名稱": "中華心靈五術文化教育學會",
    "現任理事長": "張之怡",
    "理事長屆次": "1",
    "理事長任期": "102-11-10",
    "成立日期": "102-11-10",
    "核准立案字號": "1030066266",
    "團體狀態": "已立案",
    "郵遞區號": "100",
    "會址": "臺北市中正區忠孝西路1段72號9樓之7",
    "電話": "02-2732-2917",
    "會員人數": "30",
    "會員代表人數": "0",
    "宗旨": "修心修性，諾己助人。\r\n孝道倫理，家庭福樂。\r\n言道睿行，社會圓融。\r\n雁觀奇美，智渡法眾。\r\n慈悲濟世，慧靜定恆。",
    "任務": "一、聯絡會員情誼，凝聚會員之經驗、學識與知慧，增進學術交流。\r\n二、舉辦海內外命理、陽宅、風水、易經卜卦、能量磁場等專業課程教學。\r\n三、舉辦海內外心靈成長、人際關係研究、情緒與壓力管理、生涯規劃與終身學習、企業員工專業自信養成、工作效率及團隊經營與合作、生命教練、領特質培訓等輔導專案計畫及管理。\r\n四、配合政府宣導政令。\r\n五、不定期舉辦海內外協助弱勢團體、公益性活動，協助弱勢團體，貢獻回饋鄉里。\r\n六、邀請世界各國、大陸地區及香港、澳門之專業人土來台、參訪及進行心靈五術文化教育等有關之學術研討會、演講、會議、展覽及其他公益性活動、聯誼座談會。",
    "全國性\/地區性": "全國性",
    "行政區": "臺北市"
}