{
    "團體類型": "社會團體",
    "團體分類": "社會服務及慈善團體",
    "團體名稱": "中華認輔關懷協會",
    "現任理事長": "葉宓章",
    "理事長屆次": "1",
    "理事長任期": "96-11-06",
    "成立日期": "96-11-06",
    "核准立案字號": "0960191756",
    "團體狀態": "已立案",
    "郵遞區號": "408",
    "會址": "臺中市南屯區東興路二段186號11樓之6",
    "電話": "04-22333773",
    "會員人數": "53",
    "會員代表人數": "0",
    "宗旨": "協助並訓練認輔老師及社會熱心公益的志工，以關懷在校園中需要認養輔導的孩童為宗旨，進而服務及關懷其家庭並孩童，強化家庭功能以造福社會。",
    "任務": "一.協助並提供志願服務者各項培訓。\r\n二.訓練專業認輔志工協助學校及班導師處理情緒或行為差異的學生並提升志工素養。\r\n三.協助國小設置常態認輔系統，提升親師關係、發揮影響力、改善學生及家庭的問題。",
    "全國性\/地區性": "全國性",
    "行政區": "臺中市"
}