{
    "團體類型": "社會團體",
    "團體分類": "社會服務及慈善團體",
    "團體名稱": "臺灣慧行志工救生游泳協會",
    "現任理事長": "劉雪筠",
    "理事長屆次": "4",
    "理事長任期": "104-12-05",
    "成立日期": "93-12-25",
    "核准立案字號": "0940004844",
    "團體狀態": "已立案",
    "郵遞區號": "320",
    "會址": "桃園市中壢區志廣路87號",
    "電子郵件": "twaalssa@yahoo.com.tw",
    "會員人數": "0",
    "會員代表人數": "0",
    "宗旨": "發展水上安全，普及救生教育，推廣游泳運動、培育水上救生人員，發揮救災功能，拯救水難，維護水上安全，倡導熱愛生命、發揮生命價值為宗旨。",
    "任務": "舉辦水上救生人員教練及救生員及初級救生員之訓練事項，建立考試、證照核發與覆檢事項，並推廣水上救生教育，服務社會\r\n協助消防機關從事防、就溺事項。\r\n辦理其他有關水上救生及游泳活動配合事項等等。",
    "全國性\/地區性": "全國性",
    "行政區": "桃園市"
}