{
    "團體類型": "社會團體",
    "團體分類": "同學校友會",
    "團體名稱": "中華民國國立暨南國際大學公共行政與政策學系系友會",
    "現任理事長": "許柏凱",
    "理事長屆次": "1",
    "理事長任期": "102-06-22",
    "成立日期": "102-06-22",
    "核准立案字號": "1020254766",
    "團體狀態": "已立案",
    "郵遞區號": "545",
    "會址": "南投縣埔里鎮大學路1號人文學院3樓",
    "電子郵件": "tontonyaya@hotmail.com",
    "會員人數": "45",
    "會員代表人數": "0",
    "宗旨": "以凝聚系友情誼，強化系友合作，促進系友間事業互助並協助母系發展為宗旨。",
    "任務": "一、建構系友聯繫平台，強化系友情誼。\r\n二、協助輔導系友進修及就業，謀求系友福利。\r\n三、協助母系及系友會會務發展。\r\n四、協助強化系際聯繫，促進交流合作。\r\n五、其他有關協助本系發展事項。",
    "全國性\/地區性": "全國性",
    "行政區": "南投縣"
}