{
    "團體類型": "社會團體",
    "團體分類": "宗教團體",
    "團體名稱": "台灣圓道佛教文化交流協進會",
    "現任理事長": "廖于文",
    "理事長屆次": "2",
    "理事長任期": "103-03-31",
    "成立日期": "100-04-02",
    "核准立案字號": "1000097615",
    "團體狀態": "已立案",
    "郵遞區號": "804",
    "會址": "高雄市鼓山區美術東八街8號2樓",
    "電話": "02-25633382",
    "會員人數": "100",
    "會員代表人數": "0",
    "宗旨": "本會秉持著佛教慈悲濟世之精神教化人心，並關懷社會各階層，及推動多元文化交流，以促進全國及國際之宗教融合為本會宗旨。",
    "任務": "一、推動佛教教育文化工作、慈善及各項佛教事務，落實社會之整體關懷。\r\n二、為提昇社會大眾精神層次之素養，淨化身心，開設性靈成長相關之多元化課程，如禪修班、經典研究班、禪修營、夏令營等。\r\n三、舉辦國際文化交流活動，促進台灣與國際間之文化交流，如:國際學術文化研討會、文化藝術交流訪問等。\r\n四、法寶流通，助印經書，並提供獎助金予優異在學青少年。\r\n五、推廣素食護生齋戒祈福活動。\r\n六、舉辦才藝健康休閒活動。如花藝、書法、語言學習探討&hellip;。\r\n七、協助社會大眾身心安頓，以佛教的慈悲、智慧淨化人心，促進社會和諧，使人人得以有安定和樂的生活。",
    "全國性\/地區性": "全國性",
    "行政區": "高雄市"
}