{
    "團體類型": "社會團體",
    "團體分類": "學術文化團體",
    "團體名稱": "臺灣鑑識科學學會",
    "現任理事長": "張維敦",
    "理事長屆次": "8",
    "理事長任期": "105-09-12",
    "成立日期": "91-09-14",
    "核准立案字號": "0910033373",
    "團體狀態": "已立案",
    "郵遞區號": "333",
    "會址": "桃園市龜山區33304大崗村樹人路56號中央警察大學科學館301室",
    "電話": "03-3286136",
    "傳真": "03-3286138",
    "電子郵件": "tafs@mail.cpu.edu.tw",
    "網址": "http:\/\/tafs.cid.cpu.edu.tw\/",
    "會員人數": "329",
    "會員代表人數": "0",
    "宗旨": "為推廣鑑識科學知識，提昇鑑識科學水準，確保司法審判品質。",
    "任務": "一、推動鑑識科學認證制度。\r\n二、舉辦鑑識科學學術研討會及研習會。\r\n三、促進國內外鑑識科學學術交流。\r\n四、發行鑑識科學學術期刊。\r\n五、研發鑑識科學專業技術。\r\n六、提供鑑識科學專業諮詢。\r\n七、其他與章程所訂宗旨及任務相關事項。",
    "全國性\/地區性": "全國性",
    "行政區": "桃園市"
}