{
    "團體類型": "社會團體",
    "團體分類": "經濟業務團體",
    "團體名稱": "台灣自由軟體創新應用策進會",
    "現任理事長": "鄭余鎮",
    "理事長屆次": "1",
    "理事長任期": "94-07-29",
    "成立日期": "94-07-29",
    "核准立案字號": "0940033888",
    "團體狀態": "已立案",
    "郵遞區號": "100",
    "會址": "臺北市中正區鎮江街5號6樓",
    "會員人數": "0",
    "會員代表人數": "0",
    "宗旨": "為增進會員專業知識，發展推廣國內外自由軟體相關產業事業促進經濟發展，協調同好、同業關係，增進共同利益及舉辦對自由軟體創新應用發展有益之各項活動。",
    "任務": "一、提供自由軟體研發及科技產業政策規劃、制度建立及相關法令研究等建議事項、業務之統計發展事項。\r\n二、國內外自由軟體及科技事業之聯繫、介紹、推廣等事項。\r\n三、扶植本會成員與外部廠商合作，並提供必需的顧問諮詢，以求提昇科技產業的競爭力及開拓市場。",
    "全國性\/地區性": "全國性",
    "行政區": "臺北市"
}