{
    "團體類型": "社會團體",
    "團體分類": "經濟業務團體",
    "團體名稱": "中華飛雁創業互助協會",
    "現任理事長": "王文珠",
    "理事長屆次": "6",
    "理事長任期": "105-12-17",
    "成立日期": "95-06-03",
    "核准立案字號": "0950121676",
    "團體狀態": "已立案",
    "郵遞區號": "235",
    "會址": "新北市中和區235員山路135號",
    "電話": "02-27323381",
    "會員人數": "133",
    "會員代表人數": "0",
    "宗旨": "本會為依法設立、非以營利為目的之社會團體，有遵守本國法令之權利與義務。並以發展婦女之創業才智，結合有志創業婦女之力量，整合社會資源，互相扶持，協助推廣經貿事務，創造彼此成功的機會與成長，以發揚女性創業家精神為宗旨。",
    "任務": "一、協助婦女創業問題諮商（如：行業選擇、如何設立、資金籌措等協助）。 二、透過會務活動，以發展並提高婦女之領導潛能。 \r\n三、藉參與計劃及執行會務活動，促進會員間異業結合與交流。（如：兩岸華人及國際間之創業交流）\r\n四、善用人力資源，結合政府相關機構、民間團體或個人力量，提供就業機會，促進濟發展。 \r\n五、提供婦女創業學習、進修之專業課程及經驗傳承，實務分享。\r\n六、不定期辦理經貿專業訓練課程，提升產業知能。\r\n七、整合資源，協助會員推廣貿易業務，拓展海內外市場。 \r\n八、其他與本會相關事項之任務。",
    "全國性\/地區性": "全國性",
    "行政區": "新北市"
}