{
    "團體類型": "社會團體",
    "團體分類": "環保團體",
    "團體名稱": "台灣海龍王愛地球協會",
    "現任理事長": "林愛龍",
    "理事長屆次": "1",
    "理事長任期": "102-07-07",
    "成立日期": "102-07-07",
    "核准立案字號": "1020268472",
    "團體狀態": "已立案",
    "郵遞區號": "231",
    "會址": "新北市新店區231花園六路12之403號",
    "電話": "0911-711-733",
    "會員人數": "33",
    "會員代表人數": "0",
    "宗旨": "本會為依法設立、非以營利為目的之社會團體，以人類與海洋及大自然生態永續與和諧共存為願景。透過愛護海洋，提昇人類珍惜地球生態與動物之意識，創造人類與萬物幸福豐盛的自然合諧環境為宗旨。",
    "任務": "一、關注一切影響台灣海洋生態與海洋資源永續之來源，包括來自海洋、陸地\r\n    與大氣的干擾源與汙染源等等。\r\n二、積極與政府機關、社會人士、企業團體合作，落實永續海洋資源之理念。\r\n三、積極關注海洋政策與相關環保法律，建立從海洋出發之環保機制。\r\n四、建立海洋與環保資訊交流機制，與官方、產業、學界分享正向保育經驗。\r\n五、推動永續漁業與有機農業，並與不同環境保育領域進行文化與經驗交流。\r\n六、依據社會需求，規劃辦理各項海洋活動、環境教育、文化公益、靈性生態\r\n    暨其他創新之服務與活動，以推廣永續生活與綠色消費之概念。\r\n七、參與國際環保團體合作機會，提升台灣國際地位。",
    "全國性\/地區性": "全國性",
    "行政區": "新北市"
}