{
    "團體類型": "社會團體",
    "團體分類": "宗親會",
    "團體名稱": "台灣上砂莊氏宗親會",
    "現任理事長": "莊旭賢",
    "理事長屆次": "2",
    "理事長任期": "106-02-19",
    "成立日期": "102-10-27",
    "核准立案字號": "1030129729",
    "團體狀態": "已立案",
    "郵遞區號": "351",
    "會址": "苗栗縣頭份市蟠桃里93-4號",
    "電話": "0952-452-763",
    "會員人數": "89",
    "會員代表人數": "0",
    "宗旨": "以崇宗敬祖，敦睦宗誼，秉持互助共榮之精神，謀宗族間之團結，結合全國宗親，發揚倫理道德，惕勵後進，宣揚政府政策，服務社會，維護國策為宗旨。",
    "任務": "一、關於春季祭祖及農曆四月二十日紀念法、功二祖誕辰祭祀慶典事宜。\r\n二、關於管理莊氏祖祠。\r\n三、關於族譜之編修事項。\r\n四、關於宗親之調查、登記及聯誼事項。\r\n五、關於宗親互助慶弔事宜。\r\n六、關於辦理符合本會宗旨及其他事項。",
    "全國性\/地區性": "全國性",
    "行政區": "苗栗縣"
}