{
    "團體類型": "社會團體",
    "團體分類": "學術文化團體",
    "團體名稱": "中華教育發展協會",
    "現任理事長": "鄭龍水",
    "理事長屆次": "1",
    "理事長任期": "102-11-09",
    "成立日期": "102-11-09",
    "核准立案字號": "1030102165",
    "團體狀態": "已立案",
    "郵遞區號": "100",
    "會址": "臺北市中正區和平西路一段88號12樓",
    "電話": "02-23640885",
    "會員人數": "0",
    "會員代表人數": "0",
    "宗旨": "以推動並促進台灣和大陸學生、教育人員、教育團體、組織、學生之交流並提昇教育品質為目的。",
    "任務": "促進台灣地區和大陸地區教育團體有關教育人員、組織之交流工作。\r\n促進台灣地區和大陸地區學生之交流參訪。\r\n促進大陸地區學生，包括幼兒、小學、初中、高中、大學本科、碩博士等赴台就學。\r\n促進大陸地區學生，包括幼兒、小學、初中、高中、大學本科、碩博士等赴大陸地區就學。\r\n促進台灣地區和大陸地區有關教育事業之交流、合作與發展。\r\n在台灣地區或大陸地區舉辦各項有關教育之活動，包括學校介紹、論壇、會議等。\r\n台灣各類師資赴大陸培訓暨大陸各類師資赴台工作。\r\n推動並促進台灣地區和大陸地區各項有關教育工作。",
    "全國性\/地區性": "全國性",
    "行政區": "臺北市"
}