{
    "團體類型": "社會團體",
    "團體分類": "醫療衛生團體",
    "團體名稱": "中華醫療科技協會",
    "現任理事長": "楊富美",
    "理事長屆次": "7",
    "理事長任期": "106-05-20",
    "成立日期": "84-08-02",
    "核准立案字號": "8424014",
    "團體狀態": "已立案",
    "會址": "臺北市復興南路2段27號11樓之7",
    "電話": "0938618018",
    "傳真": "02-29213577",
    "電子郵件": "aaa.yes@msa.hinet.net",
    "會員人數": "62",
    "會員代表人數": "0",
    "宗旨": "協同醫學界及相關各界共同致力促進醫療科技發展，以提昇醫療水準造福全民。",
    "任務": "協調整合產、官、學共同研發醫療科技。\r\n協助政府健力完整國家醫療品質安全標準。\r\n評鑑醫療器材、器械，並獎勵優良產品級糾舉低劣產品等等。",
    "全國性\/地區性": "全國性",
    "行政區": "臺北市"
}