{
    "團體類型": "社會團體",
    "團體分類": "學術文化團體",
    "團體名稱": "中華健康生活咖啡文化推廣發展協會",
    "現任理事長": "林美娥",
    "理事長屆次": "1",
    "理事長任期": "98-08-09",
    "成立日期": "98-08-09",
    "核准立案字號": "0980161648",
    "團體狀態": "已立案",
    "郵遞區號": "235",
    "會址": "新北市中和區中山路二段30號5樓之1",
    "電話": "02-82453200",
    "傳真": "0910119210",
    "電子郵件": "hitracy@ms75.hinet.net",
    "會員人數": "33",
    "會員代表人數": "0",
    "宗旨": "透過聯誼結合具有服務專長之理想專業人士、退休族群，鼓勵培養服務之理想，鼓勵培養服務之理想，應用於個人事業及社會之生活，滿足民眾「健康休閒、職業聯誼、人文關懷」交流，建立社會正確的價值觀念、推動國內健康養生、品質生活，奉獻個人專長，促進社會和諧與進步。",
    "任務": "推動社會大眾了解咖啡知識文化，有益身心健康提升生活品味。\r\n建構聯誼交流平台，推動健康休閒、養生、環保概念之生活品質。\r\n有關咖啡與健康、養生、環保、有聲影像、書籍刊物出版與發行等等。",
    "全國性\/地區性": "全國性",
    "行政區": "新北市"
}