{
    "團體類型": "社會團體",
    "團體分類": "社會服務及慈善團體",
    "團體名稱": "中華民國消費者健康安全協會",
    "現任理事長": "陸南莉",
    "理事長屆次": "3",
    "理事長任期": "104-01-18",
    "成立日期": "95-11-13",
    "核准立案字號": "0950187815",
    "團體狀態": "已立案",
    "郵遞區號": "801",
    "會址": "高雄市前金區801河南二路160號13樓之2",
    "電子郵件": "c075614648@yahoo.com.tw",
    "會員人數": "61",
    "會員代表人數": "0",
    "宗旨": "以保護消費者權益，推行消費者教育為宗旨，並以保障消費者健康安全為最高原則；鼓勵製造商品及提供服務之企業經營者，於商品及服務進入市場時，能確保產品之安全性，此會可作為企業體及消費者之最佳溝通平台。",
    "任務": "商品或服務品質。\r\n價格之調查、比較、研究、發表，消費者保護刊物之編印發行。\r\n定期舉辦優良企業選拔及表揚活動。",
    "全國性\/地區性": "全國性",
    "行政區": "高雄市"
}