{
    "團體類型": "社會團體",
    "團體分類": "社會服務及慈善團體",
    "團體名稱": "中華臺灣原住民體育休閒文化藝術發展協會",
    "現任理事長": "伍新國",
    "理事長屆次": "6",
    "理事長任期": "104-01-24",
    "成立日期": "88-04-24",
    "核准立案字號": "8881028",
    "團體狀態": "已立案",
    "郵遞區號": "313",
    "會址": "新竹縣尖石鄉31341錦屏村6鄰18號",
    "電話": "03-5841073",
    "傳真": "03-5841049",
    "電子郵件": "umav55@yahoo.com.tw",
    "會員人數": "500",
    "會員代表人數": "0",
    "宗旨": "一、\t加強原住民健康體魄，協助原住民發展正當休閒活動，傳承住民優良傳統文化藝術，與建立原住民優良形象。\r\n二、\t促進原住民社區生活素質，配合相關單位推展、延續原住民傳統文化教育、建立、造就永續發展的部落特色，達到總體營造的目的。",
    "任務": "一、\t結合原住民力量，促進互助合作，服務社會，造福人群。\r\n二、\t提倡原住民運動，舉辦各種聯誼活動，提升生活品質。\r\n三、\t籌措公益基金、捐助建設本會會館以提供原住民發展體育休閒文化藝術活動。\r\n四、\t建立有關部落歷史、地理、環境、族群人口等人文資料。\r\n五、\t推展部落文化及建立部落觀光文化，推展第二就業機會。\r\n六、\t加強清寒、單親、老年、酗酒家庭之援助及輔導。\r\n七、\t配合政府維護山林、河川、生態保育工作。",
    "全國性\/地區性": "全國性",
    "行政區": "新竹縣"
}