{
    "團體類型": "社會團體",
    "團體分類": "學術文化團體",
    "團體名稱": "中華傳統文化技藝協會",
    "現任理事長": "黃品璋",
    "理事長屆次": "1",
    "理事長任期": "98-11-25",
    "成立日期": "98-11-25",
    "核准立案字號": "0980241348",
    "團體狀態": "已立案",
    "郵遞區號": "830",
    "會址": "高雄市鳳山區林森路156巷29號",
    "電話": "07-7689015",
    "傳真": "0985865477",
    "電子郵件": "apls@xuite.net",
    "會員人數": "61",
    "會員代表人數": "0",
    "宗旨": "保存傳統義務文化風貌及整合相關產業，使資源共享共存，協助各傳統文化及民間藝術傳承，教導弱勢族群、老人、單親家庭、身心障礙者、受虐婦女及兒童學習專長及技能研習，創造美好社會，提昇國人優質文化。",
    "任務": "推廣傳統文化民俗技藝。\r\n發揚中華故有傳統文化，如陶藝、雕塑、國畫、書法、編織、傳統美食等。\r\n推動各地方策略聯盟，環境改善，振興地方休閒產業，規劃自然生態旅遊等相關事宜等等。",
    "全國性\/地區性": "全國性",
    "行政區": "高雄市"
}