{
    "團體類型": "社會團體",
    "團體分類": "體育運動團體",
    "團體名稱": "中華民國海洋工程暨潛水訓練協會",
    "現任理事長": "張明福",
    "理事長屆次": "1",
    "理事長任期": "96-10-22",
    "成立日期": "96-10-22",
    "核准立案字號": "0960192464",
    "團體狀態": "已立案",
    "郵遞區號": "251",
    "會址": "新北市淡水區淡金路一段180-1號1樓",
    "會員人數": "0",
    "會員代表人數": "0",
    "宗旨": "結合國內產管學界資源建構一個整合性的人力、裝備、技術與訓練平台，以配合學術研究機構從事海洋工程暨潛水技術研究發展、促進國內相關產業技術與能量提昇、協助政府相關海洋事務之規劃與執行。",
    "任務": "一、接受政府機關、學術研究機構、海洋工程暨潛水相關產業委託辦理水下專業技能與潛水人員訓練。\r\n二、接受政府機關、學術研究機構、海洋工程暨潛水相關產業委託辦理裝備、設備、儀器、機具、材料、水下工程、水下考古、水文資料、海洋環境等之安裝、佈放、實驗、測試、驗證、施工、驗收、勘察、測量、攝影、記錄、採樣等工作。",
    "全國性\/地區性": "全國性",
    "行政區": "新北市"
}