{
    "團體類型": "社會團體",
    "團體分類": "社會服務及慈善團體",
    "團體名稱": "中華聖莊靈舍協會",
    "現任理事長": "劉黃芬",
    "理事長屆次": "2",
    "理事長任期": "105-11-12",
    "成立日期": "100-11-05",
    "核准立案字號": "1000229881",
    "團體狀態": "已立案",
    "郵遞區號": "236",
    "會址": "新北市土城區慶利街5號",
    "電話": "02-29666977",
    "會員人數": "35",
    "會員代表人數": "0",
    "宗旨": "以弘揚佛道儒古聖賢善知識真理為立基，導以純正思維正心持善之修習，使身心靈之淨化啟發有正確方向依歸，不分教別相互交流和諧團結，弘道益世倡行固有道德為宗旨。",
    "任務": "一、研理、實踐佛道儒善知識直義。\r\n二、弘揚倫理道德、淨化身心靈持善行德。\r\n三、舉辦國內外助人醒世之各項公益活動。\r\n四、舉辦與各界共同慈善理念等事項，相互交流增進社會祥和。\r\n五、興辦佛道儒文化等有關之事業。\r\n六、配合政令、推行公益慈善及文化事業。\r\n七、推動其他符合本會宗旨之事宜。",
    "全國性\/地區性": "全國性",
    "行政區": "新北市"
}