{
    "團體類型": "社會團體",
    "團體分類": "社會服務及慈善團體",
    "團體名稱": "中華民國禪林功德協會",
    "現任理事長": "吳幸芳",
    "理事長屆次": "2",
    "理事長任期": "97-08-17",
    "成立日期": "91-09-22",
    "核准立案字號": "0910032121",
    "團體狀態": "已立案",
    "郵遞區號": "261",
    "會址": "宜蘭縣頭城鎮復興路89號6樓",
    "電話": "02-87326938",
    "傳真": "02-87326938",
    "電子郵件": "a27334111@yahoo.com.tw",
    "會員人數": "43",
    "會員代表人數": "0",
    "宗旨": "本會以發揚觀世音菩薩慈悲為懷、入世濟民的精神，並致力於扶助社會弱勢團體為宗旨。",
    "任務": "辦理國內外各項慈善福利之救助事項。\r\n協助政府與民間相互之溝通與政令宣導。\r\n舉辦相關之活動與座談會，募集國內外社會善心人士捐款，辦理慈善福利各項捐助事項等等。",
    "全國性\/地區性": "全國性",
    "行政區": "宜蘭縣"
}