{
    "團體類型": "社會團體",
    "團體分類": "學術文化團體",
    "團體名稱": "中華海峽兩岸中原文教經濟交流促進會",
    "現任理事長": "劉幼芬",
    "理事長屆次": "1",
    "理事長任期": "101-10-28",
    "成立日期": "101-10-28",
    "核准立案字號": "1010359940",
    "團體狀態": "已立案",
    "郵遞區號": "238",
    "會址": "新北市樹林區大義路380號15樓",
    "電話": "02-89702407",
    "會員人數": "50",
    "會員代表人數": "0",
    "宗旨": "促進海峽兩岸人民彼此認識中華文化之源流(即中原文化)，推動兩岸人民經濟、文化、教育之交流活動，並加強海峽兩岸相互瞭解與合作，以深化兩岸人民互利互惠情誼。",
    "任務": "一、舉辦兩岸經濟、文化、教育研討會。\r\n二、兩岸經濟、文化、教育之研究與發展事項。\r\n三、經濟、文化、教育之講習、觀摩及其他相關活動舉辦事項等等。",
    "全國性\/地區性": "全國性",
    "行政區": "新北市"
}