{
    "團體類型": "社會團體",
    "團體分類": "經濟業務團體",
    "團體名稱": "中華景觀設計師協會",
    "現任理事長": "鍾德頌",
    "理事長屆次": "1",
    "理事長任期": "101-12-22",
    "成立日期": "101-12-22",
    "核准立案字號": "1020085148",
    "團體狀態": "已立案",
    "郵遞區號": "404",
    "會址": "臺中市北區錦南街7號2樓",
    "電話": "04-22267929",
    "會員人數": "36",
    "會員代表人數": "0",
    "宗旨": "以促進景觀設計師之聯繫，發揚生態環保精神並為研討景觀規劃、設計、施工及其相關知能，收集與提供國內外最新景觀發展資料，集結海內外資源擴大市場與影響力，以利提升景觀設計師技術專業水準為宗旨。",
    "任務": "一、辦理與培訓專業景觀設計師人才。\r\n二、掌握景觀相關市場資訊，強化競爭能力，以利與世界接軌。\r\n三、參加相關之國際組織，國際會議並與國內外相關機構、團體聯繫合作。\r\n四、出版有關景觀專業之刊物及視聽圖文資料。",
    "全國性\/地區性": "全國性",
    "行政區": "臺中市"
}