{
    "團體類型": "社會團體",
    "團體分類": "經濟業務團體",
    "團體名稱": "中華潔淨技術協會",
    "現任理事長": "張山立",
    "理事長屆次": "6",
    "理事長任期": "105-07-23",
    "成立日期": "90-02-01",
    "核准立案字號": "0910032557",
    "團體狀態": "已立案",
    "郵遞區號": "231",
    "會址": "新北市新店區寶橋路235巷6弄1號8樓(105.11.21函報異動備查)",
    "電話": "0931789029",
    "傳真": "02-27048826",
    "電子郵件": "Tcta66@yahoo.com.tw",
    "會員人數": "0",
    "會員代表人數": "0",
    "宗旨": "以促進我國使用潔淨技術產業之整體發展，並提昇潔淨產品品質為目的之非營利社會團體; 除提供國內相關業界資訊服務及聯誼之外，並代表我國參加國際性潔淨協會會議以及學術交流等活動為宗旨。",
    "任務": "一、出版會刊及有關書籍。\r\n二、舉辦研討會、演講會、展示會及參觀活動。\r\n三、從事國內外相關產業資訊收集及提供技術交流等服務。",
    "全國性\/地區性": "全國性",
    "行政區": "新北市"
}