{
    "團體類型": "社會團體",
    "團體分類": "經濟業務團體",
    "團體名稱": "中華民國數位科技推廣協會",
    "現任理事長": "路永慧",
    "理事長屆次": "3",
    "理事長任期": "103-02-02",
    "成立日期": "95-03-18",
    "核准立案字號": "0950098415",
    "團體狀態": "已立案",
    "郵遞區號": "404",
    "會址": "臺中市北區學士路257號10樓(104年4月28日報內政部異動備查)",
    "電話": "04-22051666",
    "傳真": "04-22081818",
    "電子郵件": "dpta95@gmail.com",
    "會員人數": "48",
    "會員代表人數": "0",
    "宗旨": "以推展數位科技新知且有效應用，並協助數位科技相關產業發展為宗旨。",
    "任務": "增強數位科技發展環境與條件，得以研發、創新數位科技相關技術以提昇產業競爭力，進而推動中部地區經濟發展。\r\n推動數位化、網路化的整合，以提昇數位科技相關產業的品質與相關應用，促進數位科技相關產業經濟之發展。\r\n辦理推廣教育及專業人才培訓，以增進專業人士與數位科技推展相關結合等等。",
    "全國性\/地區性": "全國性",
    "行政區": "臺中市"
}