{
    "團體類型": "社會團體",
    "團體分類": "社會服務及慈善團體",
    "團體名稱": "台灣幸福家庭職能發展協會",
    "現任理事長": "蔡建志",
    "理事長屆次": "2",
    "理事長任期": "102-11-16",
    "成立日期": "99-11-06",
    "核准立案字號": "0990235820",
    "團體狀態": "已立案",
    "郵遞區號": "110",
    "會址": "臺北市信義區110永吉路120巷84號1樓",
    "會員人數": "74",
    "會員代表人數": "0",
    "宗旨": "本會依法設立，為非以營利為目的之社會團體，宗旨如下：「整合與家庭營造相關專業服務之社會資源，協助個人身心靈健全發展 具備『維繫家庭幸福之關鍵能力』(以下統稱為『幸福家庭職能』)，以成為稱職之家庭成員，得成就幸福家庭。」",
    "任務": "一、開辦家庭相關支持\/成長團體。二、協助家庭成員生涯規劃。三、整合或轉介家庭之相關社會資源。四、開辦專業人員之幸福家庭職能相關訓練。五、提供專業人員的就業諮詢與媒合服務。六、其他符合本會宗旨之相關服務。",
    "全國性\/地區性": "全國性",
    "行政區": "臺北市"
}