{
    "團體類型": "社會團體",
    "團體分類": "學術文化團體",
    "團體名稱": "中華民國行政顧問總會",
    "現任理事長": "黃秋陽",
    "理事長屆次": "1",
    "理事長任期": "104-11-07",
    "成立日期": "104-11-07",
    "核准立案字號": "1040085366",
    "團體狀態": "已立案",
    "郵遞區號": "100",
    "會址": "臺北市中正區重慶南路1段62號6樓",
    "電話": "0933010809",
    "會員人數": "53",
    "會員代表人數": "0",
    "宗旨": "本會以促進國際與海峽兩岸民間交流，研究國際行政事務學術文化，促進人民安和樂利，提昇國際地位與加強會員聯誼為宗旨．",
    "任務": "本會之任務如下：一、協助政府推行政令，接受政府補助與指導，提供建言。二、發揚良性政治文化，提高文明素質及孔孟之道德風範，宣傳政府優良政策，促進社會和諧發展。三、協助機關團體行政事務、業務相關之諮詢事項．四、服務會員並協助政府推展辦理下列事項：1.經貿科技之交流、推廣、合作及相關事項。2、文化藝術之交流、推廣、合作及相關事項。3.教育體育之交流、推廣、合作及相關事項。4.工商農產之交流、推廣、合作及相關事項。5.觀光旅遊之交流、推廣、合作及相關事項。6.財經建設之交流、推廣、合作及相關事項。五、舉辦學術研究及相關書刊、雜誌及報紙編譯出版事項。六、接受各界與宗旨、任務相關委託服務及交流參訪、講座論 壇、觀光旅遊、會議展覽、教育培訓、項目合作與接洽聯繫等事項．",
    "全國性\/地區性": "全國性",
    "行政區": "臺北市"
}