{
    "團體類型": "社會團體",
    "團體分類": "醫療衛生團體",
    "團體名稱": "台灣自殺防治學會",
    "現任理事長": "龍佛衛",
    "理事長屆次": "3",
    "理事長任期": "103-09-13",
    "成立日期": "97-06-21",
    "核准立案字號": "0970123652",
    "團體狀態": "已立案",
    "郵遞區號": "100",
    "會址": "臺北市中正區博愛路80號13樓(會址異動業經本部104年7月22日同意備查)",
    "電話": "02-25550500-111傅小青",
    "傳真": "02-25505065",
    "會員人數": "241",
    "會員代表人數": "0",
    "宗旨": "以自殺防治為宗旨。",
    "任務": "推展自殺防治相關教育及研究工作。\r\n舉辦自殺防治之學術性及教育性訓練。\r\n出版自殺防治相關教育性及學術性雜誌及刊物等。",
    "全國性\/地區性": "全國性",
    "行政區": "臺北市"
}