{
    "團體類型": "社會團體",
    "團體分類": "經濟業務團體",
    "團體名稱": "中南部工程領袖論壇協會",
    "現任理事長": "林秋豐",
    "理事長屆次": "1",
    "理事長任期": "105-02-19",
    "成立日期": "105-02-19",
    "核准立案字號": "1050021537",
    "團體狀態": "已立案",
    "郵遞區號": "811",
    "會址": "高雄市楠梓區高楠公路1001號",
    "電話": "07-3513121#2111",
    "傳真": "07-3513226",
    "電子郵件": "engineering.msot@gmail.com",
    "會員人數": "57",
    "會員代表人數": "5",
    "宗旨": "本會為依法設立、非以營利為目的之社會團體，以促進會員之聯繋與合作並針對我國工程教育以及中南部產業發展重要議題提出建言為宗旨。",
    "任務": "一、發展本會組織之事項。二、舉辦演講、研討會及論壇．三、接受委託辦理各項工程領域事務。四、建立智庫、凝聚專業共識，為國家建言。五、建立跨專門工程領域交流平台。六、會員聯誼互動之事項。七、推動促成本會宗旨之相關活動。",
    "全國性\/地區性": "全國性",
    "行政區": "高雄市"
}