{
    "團體類型": "社會團體",
    "團體分類": "同學校友會",
    "團體名稱": "國立空中大學生活科學系系友會",
    "現任理事長": "鄭美圓",
    "理事長屆次": "1",
    "理事長任期": "105-01-02",
    "成立日期": "104-12-20",
    "核准立案字號": "1050002875",
    "團體狀態": "已立案",
    "郵遞區號": "402",
    "會址": "臺中市南區五權南路340號",
    "電話": "0911-911806",
    "會員人數": "0",
    "會員代表人數": "0",
    "宗旨": "本會為依法設立、非以營利為目的之社會團體，以連繫系友感情，協助母系及系友之發展，提供系友相關資訊，促進學術及專業研究為宗旨。",
    "任務": "本會任務如下：一、聯絡會員、出版會員名冊及會訊。二、促進系友間在工作與生活上之互助合作。三、辦理有關會員之康樂活動及福利事項。四、協助母系系務發展及各種活動事項。五、促進學術交流，加強產學界建教合作。六、本會傑出系友之表揚。七、提供業界徵人資訊以協助系友之就業，另為業界會員提供正在尋求就業之會員資訊，作雙向服務．",
    "全國性\/地區性": "全國性",
    "行政區": "臺中市"
}