{
    "團體類型": "社會團體",
    "團體分類": "社會服務及慈善團體",
    "團體名稱": "中華淨履堂關懷服務協會",
    "現任理事長": "陳堃誌",
    "理事長屆次": "1",
    "理事長任期": "102-09-13",
    "成立日期": "102-09-13",
    "核准立案字號": "1020336298",
    "團體狀態": "已立案",
    "郵遞區號": "330",
    "會址": "桃園市桃園區富國路681巷19弄46號",
    "電話": "03-3024883",
    "會員人數": "30",
    "會員代表人數": "0",
    "宗旨": "基於對弱勢族群得關懷及生命的尊重，本會乃以博愛精神、關懷互助、發揚家庭倫理、提倡社會上需要幫助的人，促進社會和諧為成立之宗旨。",
    "任務": "一、國小、國中學校之清寒學生，學雜費、營養午餐費之補助。\r\n二、無依無靠之幼童生活補助款或學雜費或營養午餐費。\r\n三、孤苦無依老人之生活補助或物資。\r\n四、無依無謀生能力之身心障礙者者生活補助款或物資。\r\n五、突發災難者之急難救助。\r\n六、其他有意義的慈善活動與救助。",
    "全國性\/地區性": "全國性",
    "行政區": "桃園市"
}