{
    "團體類型": "社會團體",
    "團體分類": "經濟業務團體",
    "團體名稱": "中華文創暨經貿投資協會",
    "現任理事長": "周華穗",
    "理事長屆次": "1",
    "理事長任期": "105-08-10",
    "成立日期": "105-08-10",
    "核准立案字號": "1050060401",
    "團體狀態": "已立案",
    "郵遞區號": "235",
    "會址": "新北市中和區新生街112巷6號3樓",
    "宗旨": "本會未依法設立,非以營利為目的之社會團體，為凝聚更多相同理念及願意共同為台灣產業打拼人士的力量，建立更豐富務實的資源平台，期望透過各地的産業網脈相連及資源共享，各會員勠力合作凝聚力量，彼此協同創造擴展兩岸中华產業開拓行銷国际商機，同時推動高端論壇，座談等多方面行銷，也藉由宏觀世界的視野凝聚共識，推動「兩岸合作平臺佈局全球」，讓台灣中小企業產業重現生機再創高峰為宗旨。",
    "任務": "一、推廣中華文化傳遞交流，提供創意人才發展推廣平台．二、舉辦優良經貿商展活動，參加海內外展覽協助企業宣傳．三、舉辦經貿交流對接洽談會，協助發展線上線下銷售通路。四、建立企業策略聯盟交流平台，舉辦企業家聯誼活動。五、提供全球華人創投融資平台，對接全球華人投資管道．六、提供會員企業各類文創、經貿暨投資諮詢服務．",
    "全國性\/地區性": "全國性",
    "行政區": "新北市"
}