{
    "團體類型": "社會團體",
    "團體分類": "醫療衛生團體",
    "團體名稱": "台灣芳香自然保健促進協會",
    "現任理事長": "胡儷瓊",
    "理事長屆次": "1",
    "理事長任期": "99-01-15",
    "成立日期": "99-01-15",
    "核准立案字號": "0990020575",
    "團體狀態": "已立案",
    "郵遞區號": "112",
    "會址": "臺北市北投區中央北路二段406號6樓",
    "電話": "02-28931779",
    "電子郵件": "aromaworld@kimo.com",
    "會員人數": "90",
    "會員代表人數": "0",
    "宗旨": "結合從事芳香精油及自然保健之生活應用，致力芳香及自然保健的推廣及普及化，以促進全民健康發展。",
    "任務": "定期舉辦芳香自然保健研習，提昇專業素養。\r\n定期舉辦芳香自然保健相關交流活動，推動芳香及自然保健研習，以及相關科普知識、衛教宣導，提升民眾對促進健康的認知及發展。\r\n與國際間學術、公民營組織交流，提升我國芳香及自然保健組織之地位等等。",
    "全國性\/地區性": "全國性",
    "行政區": "臺北市"
}