{
    "團體類型": "社會團體",
    "團體分類": "社會服務及慈善團體",
    "團體名稱": "台灣就業職能發展協會",
    "現任理事長": "楊純貞",
    "理事長屆次": "1",
    "理事長任期": "101-06-17",
    "成立日期": "101-06-17",
    "核准立案字號": "1010265972",
    "團體狀態": "已立案",
    "郵遞區號": "540",
    "會址": "南投縣南投市光明南路72巷82號",
    "電話": "0980360059",
    "電子郵件": "a2332767@yahoo.com.tw",
    "會員人數": "35",
    "會員代表人數": "0",
    "宗旨": "結合國內廠商及全國產、官、學、研各界菁英賢達，以建立職能訓練為基礎，從而推動台灣就業市場發展，安定經濟為目標，期盼增進在職員工、朱業者、弱勢族群及青少年之專業技能及知識以提升競爭力。改善勞動條件及生活、並協助政府推行政釙政策為最高宗旨。",
    "任務": "一、辦理政府有關單位委辦之學術與公益服務活動及職業訓練課程。\r\n二、促進就業市場資訊流通，推動求才企業與人力資源整合應用。\r\n三、其他符合本會設立宗旨之相關公益性教育事務等等。",
    "全國性\/地區性": "全國性",
    "行政區": "南投縣"
}