{
    "團體類型": "社會團體",
    "團體分類": "學術文化團體",
    "團體名稱": "中華藝術文化數位動漫海外推廣協會",
    "現任理事長": "陳彥蓁",
    "理事長屆次": "3",
    "理事長任期": "105-05-15",
    "成立日期": "96-05-25",
    "核准立案字號": "0960102398",
    "團體狀態": "已立案",
    "郵遞區號": "105",
    "會址": "臺北市松山區民福里民族東路707號",
    "電話": "02-25471822",
    "傳真": "02-25468175",
    "會員人數": "43",
    "會員代表人數": "0",
    "宗旨": "一、秉持中華藝術推展之理念，協助政府將數位動漫之典藏與文化，推廣至海外各地。\r\n二、促進與海外各國際之間的動漫文化交流與推廣。\r\n三、提升民眾對於中華藝術之傳統文化典藏數位動漫的瞭解與喜愛，以及提供數位動漫創作者一個廣大伸展的舞台。",
    "任務": "一、協助政府推行政令，發揚民主精神。\r\n二、協助政府推動數位動漫之保存與發揚，並協助政府之相關宣導數位化。\r\n三、以永續經營之理念，協助推動各項數位文化之建設工作、藝術活動。",
    "全國性\/地區性": "全國性",
    "行政區": "臺北市"
}