{
    "團體類型": "社會團體",
    "團體分類": "學術文化團體",
    "團體名稱": "台灣高中哲學教育推廣學會",
    "現任理事長": "吳豐維",
    "理事長屆次": "2",
    "理事長任期": "104-11-29",
    "成立日期": "102-11-21",
    "核准立案字號": "1020376607",
    "團體狀態": "已立案",
    "郵遞區號": "111",
    "會址": "臺北市士林區中正路236巷26號6樓",
    "電話": "02-88096151",
    "電子郵件": "roxymow@gmail.com",
    "會員人數": "0",
    "會員代表人數": "0",
    "宗旨": "本會為依法設立、非以營利為目的之社會團體．本學會成立宗旨為：推廣促進高中哲學教育、高中哲學教育師資培力，並以高中哲學教育為基礎，普及哲學教育．",
    "任務": "一、以各種形式推廣促進高中哲學教育。二、高中哲學教育師資培力。三、研究各國哲學教育制度發展與歷史概況。四、推廣哲學教育與現有高中學科的合作、對話，進行跨科際整合交流。五、推廣哲學教育與公民社會議題的結合、對話。六、舉辦各類哲學教育講座，提昇高中生對於哲學的興趣與認知。七、發行哲學教育性刊物、哲學教育叢書及資訊、各式宣傳品。八、接受委託、代辦各種哲學教育推廣諮詢等服務。九、其他有關達成本會宗旨事項。",
    "全國性\/地區性": "全國性",
    "行政區": "臺北市"
}