{
    "團體類型": "社會團體",
    "團體分類": "學術文化團體",
    "團體名稱": "中華國際時尚美學育成協會",
    "現任理事長": "盧永茵",
    "理事長屆次": "3",
    "理事長任期": "104-09-20",
    "成立日期": "100-03-17",
    "核准立案字號": "1000077426",
    "團體狀態": "已立案",
    "郵遞區號": "235",
    "會址": "新北市中和區235中正路932號2樓",
    "電話": "02-22239339",
    "會員人數": "0",
    "會員代表人數": "0",
    "宗旨": "本會宗旨為致力於研究及改造目前國內時尚美學之水準，落實時尚美學大眾化，打造時尚美學地球村並與國際時尚美學接軌。",
    "任務": "一、研究並推廣成為大眾化之時尚美學教學，開創新生活時尚美學。\r\n         二、研究、開發及出版時尚美學影音、相關教材、網路資訊。\r\n         三、研究原住民、客家等不同文化之時尚美學。\r\n         四、辦理時尚美學教學相關之學術研討會、交流、觀摩、座談等。\r\n         五、辦理師資之培訓，並提供相關資訊。\r\n         六、協助專業時尚美學之藝術人才，考取相關證照。\r\n         七、協助各項時尚美學檢定與學藝競賽。\r\n         八、促進國內、外及兩岸時尚美學教學及教育之交流。\r\n         九、促使時尚美學人才與在地文化活動結合，推動時尚產業經濟發展。\r\n         十、提供本會會員相關法務諮詢。\r\n         十一、提供及協助各時尚美學遊學資訊。\r\n         十二、舉辦各媒體、電視、網路、雜誌、展覽活動，讓時尚美學與多\r\n               元媒體結合，創造時尚潮流的價值。\r\n         十三、舉辦各種族時尚美學研究、交流、觀摩、研習、社教藝文活動。\r\n         十四、培育時尚美學藝術人才素質提升，多元發展。\r\n         十五、成立時尚美學巡迴表演及慈善表演。\r\n         十六、結合身心靈與宗教，讓時尚美學與生活連結。\r\n         十七、其他與章程所定之宗旨及任務相關事項。",
    "全國性\/地區性": "全國性",
    "行政區": "新北市"
}