{
    "團體類型": "社會團體",
    "團體分類": "經濟業務團體",
    "團體名稱": "兩岸殯葬交流協會",
    "現任理事長": "張峻豪",
    "理事長屆次": "1",
    "理事長任期": "103-12-06",
    "成立日期": "103-12-06",
    "核准立案字號": "1040009832",
    "團體狀態": "已立案",
    "郵遞區號": "800",
    "會址": "高雄市新興區民生一路247號7樓之1",
    "電話": "07-2223733轉1010",
    "傳真": "07-2223732",
    "會員人數": "81",
    "會員代表人數": "0",
    "宗旨": "以兩岸殯葬文化交流與合作方式，增進兩岸殯葬業間的相互了解與友誼，提升兩岸殯葬服務行業的服務能力和服務水平為宗旨。",
    "任務": "一、舉辦兩岸殯葬行業交流工作、會議、學術研討、觀摩、會展等活動。\r\n二、整合兩岸殯葬行業經營理念。\r\n三、舉辦兩岸殯葬行業培訓等技能提升活動。\r\n四、創辦兩岸殯葬行業交流工作會刊、工作網站。",
    "全國性\/地區性": "全國性",
    "行政區": "高雄市"
}