{
    "團體類型": "社會團體",
    "團體分類": "社會服務及慈善團體",
    "團體名稱": "台灣愛之希望協會",
    "現任理事長": "黃志中",
    "理事長屆次": "5",
    "理事長任期": "104-12-05",
    "成立日期": "88-09-04",
    "團體狀態": "已立案",
    "郵遞區號": "804",
    "會址": "高雄市鼓山區龍文街31號5樓",
    "電子郵件": "lovehope@seed.net.tw",
    "會員人數": "0",
    "會員代表人數": "0",
    "宗旨": "關懷愛滋病感染者，提供持續性的服務與支持，解決因愛滋病蔓延所帶來的社會及醫療上的問題。\r\n推廣愛滋防治活動與教育，提高民眾對愛滋病的認識、瞭解與關切。",
    "任務": "電話諮詢；提供有關愛滋病相關資訊解答雨情緒支持。\r\n協助匿名篩檢活動之推行。\r\n培訓志工：公益活動及志工教育課程的舉辦等等。",
    "全國性\/地區性": "全國性",
    "行政區": "高雄市"
}