{
    "團體類型": "社會團體",
    "團體分類": "宗教團體",
    "團體名稱": "台灣欽哲旺波學佛會",
    "現任理事長": "賴玉琳",
    "理事長屆次": "2",
    "理事長任期": "97-05-31",
    "成立日期": "93-05-22",
    "核准立案字號": "0930072865",
    "團體狀態": "已立案",
    "郵遞區號": "408",
    "會址": "臺中市南屯區黎明路1段互愛巷42號",
    "電話": "0922499679",
    "傳真": "04-23262515",
    "電子郵件": "milklkg@yahoo.com.tw",
    "會員人數": "42",
    "會員代表人數": "0",
    "宗旨": "以推廣藏傳佛教文化，修行利生，提倡佛話人生，淨化社會人心，端正禮俗改善社會風氣促進社會祥和，興辦佛教文化事業及佛教教育，與辦佛教講座及推動社會慈善公益救助為宗旨。",
    "任務": "推廣藏傳佛教本土化，直接以中文進行藏傳佛教之傳授與交流。\r\n宏揚藏傳佛法，以達到淨化人心、促進社會祥和為目的。\r\n佛學講座等等。",
    "全國性\/地區性": "全國性",
    "行政區": "臺中市"
}