{
    "團體類型": "社會團體",
    "團體分類": "宗教團體",
    "團體名稱": "中華民國下密院顯密學校佛學會",
    "現任理事長": "李威德",
    "理事長屆次": "1",
    "理事長任期": "98-05-09",
    "成立日期": "98-05-09",
    "核准立案字號": "0980098137",
    "團體狀態": "已立案",
    "會址": "臺北市三民路62巷5號6樓",
    "傳真": "02-25285822",
    "會員人數": "100",
    "會員代表人數": "0",
    "宗旨": "本會以提高國人佛學文化藝術內涵，淨化社會人心，提倡倫理道德，提升生活品質與人文素養，啟迪心靈智慧，激發慈悲精神，協助推廣心靈成長，生命內涵，文化藝術及終身學習教育等公益活動為宗旨。",
    "任務": "一、贊助或舉辦國內外佛教文化，藝術，教育，生命等公益事業。\r\n二、贊助或設立佛學文化或文物藝術中心。\r\n三、贊助或出版及翻譯有益身心靈成長或佛學文化藝術之書刊。\r\n四、贊助或舉辦促進身心靈健康之佛教文化藝術教育活動或休閒活動。\r\n五、提供獎學金及助學金，獎助優秀之出家，在家眾。\r\n六、提供獎助學金，獎助優秀之社會，文化教育，藝術工作者。\r\n七、辦理或協助社區之佛教文化藝術公益事業。\r\n八、其他符合本會設立宗旨之相關公益性佛教文化藝術活動。",
    "全國性\/地區性": "全國性",
    "行政區": "臺北市"
}