{
    "團體類型": "社會團體",
    "團體分類": "社會服務及慈善團體",
    "團體名稱": "中華民國生命飛揚關懷協會",
    "現任理事長": "黃彥穎",
    "理事長屆次": "1",
    "理事長任期": "101-03-10",
    "成立日期": "101-03-10",
    "核准立案字號": "1010182856",
    "團體狀態": "解散",
    "解散日期": "103-07-31",
    "郵遞區號": "326",
    "會址": "桃園市楊梅區青山二街327巷4號",
    "電話": "0980778408",
    "電子郵件": "a221339433@yahoo.com.tw",
    "會員人數": "62",
    "會員代表人數": "0",
    "宗旨": "喚醒社會大愛、提升社會生活品質、營造美化社區生態、單親家庭關懷、落實關懷社會弱勢族群。",
    "任務": "一、以社區總體營造為基礎，喚醒社會大愛。\r\n二、共同提昇社區生活品質。\r\n三、建立生態家園，營造環保永續社區等等。",
    "全國性\/地區性": "全國性",
    "行政區": "桃園市"
}