{
    "團體類型": "社會團體",
    "團體分類": "經濟業務團體",
    "團體名稱": "中華兩岸農業特產及經貿觀光協會",
    "現任理事長": "蕭志洋",
    "理事長屆次": "2",
    "理事長任期": "104-07-30",
    "成立日期": "101-07-27",
    "核准立案字號": "1010350777",
    "團體狀態": "已立案",
    "郵遞區號": "104",
    "會址": "臺北市中山區南京東路3段210號10樓",
    "電話": "0956159818、0952129888林德仁、02-27512410",
    "傳真": "02-27815545",
    "電子郵件": "darrenlin123@hotmail.com",
    "會員人數": "0",
    "會員代表人數": "0",
    "宗旨": "致力推廣本國農業及精特產品、經貿、觀光等方面發展，期展能對本地及區域之農林漁牧業發展與大眾健康、企業繁榮樂利、增廣民眾見聞等方面貢獻一己之力。",
    "任務": "一、推廣本國農林漁牧業及精特產品、經貿、觀光等與國人國內旅遊之發展。\r\n二、促進區域與海峽兩岸農業及特產、經貿、觀光、展覽交流及合作事宜。\r\n三、邀請大陸各省或全國農業及特產、經貿、觀光、展覽之參訪團與觀展團體來台交流。\r\n四、組織農業及特產、經貿、觀光、展覽考察團前往大陸地區，促進海峽兩岸之交流與合作;協助推薦或認證我國之農特產。\r\n五、協助培訓海峽兩岸農業及特產、經貿、觀光及展覽等人才，並推派上述人才前往海峽對岸參訪或培訓或受訓。\r\n六、舉辦海峽兩岸暨區域性之各國農業及特產、經貿、觀光等有關之展覽及研討會議等活動。\r\n七、製作相關網站、會刊、雜誌、圖書編輯或活動報導等宣傳本會。\r\n八、其他有關海峽兩岸農業及特產、經貿、觀光推廣事宜。",
    "全國性\/地區性": "全國性",
    "行政區": "臺北市"
}