{
    "團體類型": "社會團體",
    "團體分類": "學術文化團體",
    "團體名稱": "中華農業機械學會",
    "現任理事長": "雷鵬魁",
    "理事長屆次": "14",
    "理事長任期": "106-01-13",
    "成立日期": "80-01-06",
    "核准立案字號": "897244",
    "團體狀態": "已立案",
    "郵遞區號": "402",
    "會址": "臺中市南區402國光路250號(國立中興大學農業機械實習工廠轉)",
    "電話": "04-22840590",
    "傳真": "04-22857590",
    "電子郵件": "chenlh@dragon.nchu.edu.tw",
    "會員人數": "145",
    "會員代表人數": "0",
    "宗旨": "以促進農業機械之學術研究與發展為宗旨。",
    "任務": "促進國內外農業機械之學術研究、交流及合作。\r\n研究改進農業機械教育及協助人才之培養訓練。\r\n舉辦農業機械學術研討會籍推廣活動等等。",
    "全國性\/地區性": "全國性",
    "行政區": "臺中市"
}