{
    "團體類型": "社會團體",
    "團體分類": "宗教團體",
    "團體名稱": "中華民國基督教華夏好牧人關懷協會",
    "現任理事長": "吳進柱",
    "理事長屆次": "5",
    "理事長任期": "105-02-29",
    "成立日期": "92-10-19",
    "核准立案字號": "0920071903",
    "團體狀態": "已立案",
    "郵遞區號": "205",
    "會址": "基隆市暖暖區暖暖街610巷7號1樓",
    "電話": "0955018766",
    "傳真": "02-24587947",
    "電子郵件": "wcct2833@ms2.hinet.net",
    "會員人數": "50",
    "會員代表人數": "0",
    "宗旨": "協助成全海峽兩岸教會傳道人（個人靈命、教會工作、家庭生活）全面健全的發展，及對弱勢族群地區之教育、醫療和急難救助之需要。",
    "任務": "一、聖經真理課程的培訓。\r\n二、工具書的印製和發送。\r\n三、宣教士的生活費支助。",
    "全國性\/地區性": "全國性",
    "行政區": "基隆市"
}