{
    "團體類型": "社會團體",
    "團體分類": "學術文化團體",
    "團體名稱": "全球華人文化暨教育交流促進會",
    "現任理事長": "楊賀雯",
    "理事長屆次": "1",
    "理事長任期": "103-03-30",
    "成立日期": "103-03-30",
    "核准立案字號": "1030181568",
    "團體狀態": "已立案",
    "郵遞區號": "427",
    "會址": "臺中市潭子區427中山路一段一巷56弄19號",
    "電話": "04-2451-2505*4707",
    "會員人數": "0",
    "會員代表人數": "0",
    "宗旨": "以致力於推動全球華人文化暨教育交流。",
    "任務": "一、結合公私機構或團體，辦理座談、研習、講座、參訪、展覽或發表論文等方式，促進全球華人人才交流。\r\n二、透過本會平台積極建立人際網路、掌握脈動、經驗交流、資源共享。\r\n三、透過本會平台宣導並發揚台灣文化及教育相關活動。\r\n四、配合政府辦理宣導並發揚有關文化暨教育之交流政策及措施相關事項。\r\n五、其他不違背本會宗旨，經本會理監事會同意之工作事項。",
    "全國性\/地區性": "全國性",
    "行政區": "臺中市"
}