{
    "團體類型": "社會團體",
    "團體分類": "社會服務及慈善團體",
    "團體名稱": "中華繼承贈與基本權益保護協會",
    "現任理事長": "王文杞",
    "理事長屆次": "2",
    "理事長任期": "101-12-29",
    "成立日期": "97-07-26",
    "核准立案字號": "0970129652",
    "團體狀態": "已立案",
    "郵遞區號": "104",
    "會址": "臺北市中山區伊通街114號B1",
    "傳真": "02-25026526",
    "電子郵件": "brig2010_org@yahoo.com.tw",
    "會員人數": "31",
    "會員代表人數": "0",
    "宗旨": "協助維誙全國繼承贈與人權益\r\n保護弱勢繼承人、贈與人，保障其合法繼承贈與權益\n推動繼承、贈與法令宣導教育及執行",
    "任務": "一、協助維護全國人民繼承、贈與的相關權益\n二、協助及保護弱繼承、贈與人，保障其合法相關繼承、贈與權益",
    "全國性\/地區性": "全國性",
    "行政區": "臺北市"
}