{
    "團體類型": "社會團體",
    "團體分類": "體育運動團體",
    "團體名稱": "台灣艋舺跑者文化協會",
    "現任理事長": "周天寶",
    "理事長屆次": "3",
    "理事長任期": "105-06-05",
    "成立日期": "100-08-21",
    "核准立案字號": "1000230940",
    "團體狀態": "已立案",
    "郵遞區號": "108",
    "會址": "臺北市萬華區雙園街21巷14號2樓(該會於106.7.20函報內政部異動備查)",
    "會員人數": "86",
    "會員代表人數": "0",
    "宗旨": "結合有志之士，為提升跑者運動精神及文化水準，培養優秀運動人才及推廣跑者人文素養而成立。",
    "任務": "承辦及協辦各項跑步活動時，著重於跑者文化之提倡。\r\n配合國家政策提升全民對跑者文化之認識。\r\n提供國內外跑者有關跑步比賽及相關活動訊息等等。",
    "全國性\/地區性": "全國性",
    "行政區": "臺北市"
}