{
    "團體類型": "社會團體",
    "團體分類": "醫療衛生團體",
    "團體名稱": "中華緊急醫療救助協會",
    "現任理事長": "黃獻宏",
    "理事長屆次": "1",
    "理事長任期": "99-02-21",
    "成立日期": "99-02-21",
    "核准立案字號": "0990048310",
    "團體狀態": "已立案",
    "郵遞區號": "412",
    "會址": "臺中市大里區東榮路483號",
    "電話": "02-87519839轉203",
    "會員人數": "33",
    "會員代表人數": "0",
    "宗旨": "提升國民健康水平、幫助提供有效之緊急醫療救助服務，協助落實華人緊急醫療與對醫院的通報後送，在緊急災難救助的情形下幫助華人提供更完善之緊急醫療相關服務網路為目標，以及其他有助於華人緊急醫療之相關業務推動為宗旨。",
    "任務": "促進華人緊急醫療水準。\r\n協助華人緊急醫療交流。\r\n提供華人緊急醫療之建言和政策等等。",
    "全國性\/地區性": "全國性",
    "行政區": "臺中市"
}