{
    "團體類型": "社會團體",
    "團體分類": "宗教團體",
    "團體名稱": "那若子續佛學會",
    "現任理事長": "謝雷諾",
    "理事長屆次": "1",
    "理事長任期": "105-06-05",
    "成立日期": "105-06-05",
    "核准立案字號": "1050045317",
    "團體狀態": "已立案",
    "郵遞區號": "103",
    "會址": "臺北市大同區南京西路239巷27號5樓（會址異動經本部106年1月18日同意備查）",
    "宗旨": "本會為依法設立、非以營利為目的之社會團體，以依循佛陀教化之精神，推廣佛陀教育，將佛法顯諸於世，讓慈愛深植人心，時時抱持服務關懷之心，共同推動利人利己、造福增慧事業為宗旨。",
    "任務": "一、\t定期舉辦齋戒、共修、祈福、除障等法會。\r\n二、\t臨終關懷及往生助念:會員或其家屬若遇到人將往生可請師為其開示佛法與祝禱及往生助念。\r\n三、\t佛法教學:定期免費請上師依佛陀教化精神、推廣佛陀教育。",
    "全國性\/地區性": "全國性",
    "行政區": "臺北市"
}