{
    "團體類型": "社會團體",
    "團體分類": "體育運動團體",
    "團體名稱": "中華民國國榮桌球發展交流協會",
    "現任理事長": "林國榮",
    "理事長屆次": "1",
    "理事長任期": "103-02-14",
    "成立日期": "103-02-14",
    "核准立案字號": "1030116956",
    "團體狀態": "已立案",
    "郵遞區號": "106",
    "會址": "臺北市大安區106光復南路432號2樓",
    "會員人數": "30",
    "會員代表人數": "0",
    "宗旨": "本會為依法設立、非以營利為目的之社會團體，以響應中華民國政府提倡全民體育，推展桌球運動之普及發展，促進身心健康，提升桌球運動水準，並以球會友增進情誼交流和健康運動之概念為宗旨，藉由設計休閒運動競賽，培養國小、國中、高中學生及社會人士的運動興趣及技能發展。",
    "任務": "(一)、促進桌球運動教授之研究與整理。\r\n(二)、舉辦桌球教授相關之活動交誼競賽。\r\n(三)、出版有關桌球運動之雜誌書刊。\r\n(四)、推廣桌球教授技能之發展。\r\n(五)、提供桌球文化相關之策展及推廣大眾了解桌球運動。 \n(六)、辦理其他與章程所訂宗旨及任務相關事項。",
    "全國性\/地區性": "全國性",
    "行政區": "臺北市"
}