{
    "團體類型": "社會團體",
    "團體分類": "體育運動團體",
    "團體名稱": "中華民國八極拳協會",
    "現任理事長": "林松賢",
    "理事長屆次": "9",
    "理事長任期": "104-12-12",
    "成立日期": "88-11-07",
    "核准立案字號": "0950087492",
    "團體狀態": "已立案",
    "郵遞區號": "115",
    "會址": "臺北市南港區東新街180巷11號地下2層之1",
    "電話": "02-27834850",
    "電子郵件": "terrybox@pchome.com.tw",
    "會員人數": "96",
    "會員代表人數": "0",
    "宗旨": "本會以發展八極拳武術；宏揚中華民族固有武德；健全體魄，使成文武合一之國民為宗旨。",
    "任務": "一、\t研究八極拳武術傳承史料及拳術、拳理、兵器等武技。\r\n二、\t編撰及出版八極拳武術教材及其他文獻。\r\n三、\t傳授八極拳武術，統籌舉辦八極拳教練訓練及資格檢定。\r\n四、\t研訂八極拳拳術及刀、槍、劍、棍等兵器武術之比賽規則。\r\n五、\t研訂八極拳各項武技晉階升等之評訂標準及辦法。\r\n六、\t選拔及組訓代表隊參加國術比賽。",
    "全國性\/地區性": "全國性",
    "行政區": "臺北市"
}