{
    "團體類型": "社會團體",
    "團體分類": "環保團體",
    "團體名稱": "台灣美化協會",
    "現任理事長": "唐松章",
    "理事長屆次": "3",
    "理事長任期": "105-11-25",
    "成立日期": "98-02-06",
    "核准立案字號": "0980050937",
    "團體狀態": "已立案",
    "郵遞區號": "111",
    "會址": "臺北市士林區中山北路6段90號4樓A室",
    "傳真": "02-28370063",
    "會員人數": "273",
    "會員代表人數": "0",
    "宗旨": "藉由清掃活動，由清潔的動作中能體會，成為謙虛、細心、容易感動的人，讓感謝的新萌芽，塑造真誠的社會文化，且充實個人心靈，帶動良好社會風氣創造共好的社會、取之於社會，用之於社會。塑造「良樹細根」、「凡事徹底」精神。",
    "任務": "每季安排不同單位區域進行美化環境清掃動作。\r\n清掃活動結束後，進行小組清掃體驗分享。\r\n推廣清潔理念，由中體會凡事撤體、培養容易感動的心。",
    "全國性\/地區性": "全國性",
    "行政區": "臺北市"
}