{
    "團體類型": "社會團體",
    "團體分類": "宗教團體",
    "團體名稱": "中華民國亞洲福樂宣教中心協會",
    "現任理事長": "陳學平",
    "理事長屆次": "1",
    "理事長任期": "94-07-17",
    "成立日期": "94-07-17",
    "核准立案字號": "0940030321",
    "團體狀態": "已立案",
    "郵遞區號": "251",
    "會址": "新北市淡水區中正路57號2樓",
    "電話": "02-26202845",
    "會員人數": "0",
    "會員代表人數": "0",
    "宗旨": "以基督無條件大愛之大能，見證傳承於新會員，訓練他們用各種無條件的方式，再去協助更多家庭得著福樂人生，社區和國家因而更趨福樂。",
    "任務": "一、發掘有基督大愛的人為基本會員而加以適當訓練。\r\n二、協助尚未有基督大愛的人得此生命並加以適當訓練。\r\n三、督導各地分會之發展，評估對家庭福樂和社會福樂之實際貢獻。",
    "全國性\/地區性": "全國性",
    "行政區": "新北市"
}