{
    "團體類型": "社會團體",
    "團體分類": "經濟業務團體",
    "團體名稱": "台灣金針協會",
    "現任理事長": "吳顯權",
    "理事長屆次": "7",
    "理事長任期": "105-04-10",
    "成立日期": "92-07-28",
    "核准立案字號": "0920034222",
    "團體狀態": "已立案",
    "郵遞區號": "981",
    "會址": "花蓮縣玉里鎮樂合里新民13之1號",
    "電話": "0933998259",
    "傳真": "03-8889378",
    "電子郵件": "lds104inn@yahoo.com.tw",
    "會員人數": "0",
    "會員代表人數": "0",
    "宗旨": "本會為依法設立，非以營利為目的之社會團體，並以提升金針產業競爭力，保障消費者權益，建立產業新形象，促進金針產業永續發展。",
    "任務": "生產之研究改良與發展，產品之調查，統計及產銷調節，保障會員合法權益，輔導會員降低生產成本，提升產業競爭力。協助會員申辦政府各項低利貸款，協助推廣會員生產衛生，安全之優質產品及辦理消費者教育事項。協助產業蒐集相關資訊，積極推動國內外促銷工作，協調處理同業間之糾紛，聯絡會員感情及舉辦會員福利活動，舉辦與會員有關之各項公益事業活動。",
    "全國性\/地區性": "全國性",
    "行政區": "花蓮縣"
}