{
    "團體類型": "社會團體",
    "團體分類": "學術文化團體",
    "團體名稱": "台灣制度與經濟史學會",
    "現任理事長": "吳聰敏",
    "理事長屆次": "2",
    "理事長任期": "105-10-31",
    "成立日期": "104-10-17",
    "核准立案字號": "1040093176",
    "團體狀態": "已立案",
    "郵遞區號": "106",
    "會址": "臺北市大安區羅斯福路4段1號國立臺灣大學社會科學院經濟學系系辦公室",
    "電話": "02-33663366轉55762",
    "傳真": "02-23659128",
    "電子郵件": "ntut019@ntu.edu.tw",
    "會員人數": "47",
    "會員代表人數": "0",
    "宗旨": "本會為依法設立、非以營利為目的之社會團體，以促進個多人才投入相關領域研究，並將本土議題與研究成果推上國際舞台為宗旨．",
    "任務": "一、以台灣經濟發展經驗為素材，推動制度經濟學之研究．二、鼓勵優秀人才投入相關議題研究．三、促進常態性跨國研究團隊成立．四、促進國際學術交流．五、刊物出版．",
    "全國性\/地區性": "全國性",
    "行政區": "臺北市"
}