{
    "團體類型": "社會團體",
    "團體分類": "學術文化團體",
    "團體名稱": "台灣鵗力灣協會",
    "現任理事長": "金美蘭",
    "理事長屆次": "3",
    "理事長任期": "105-01-10",
    "成立日期": "97-01-13",
    "核准立案字號": "0970029282",
    "團體狀態": "已立案",
    "郵遞區號": "403",
    "會址": "臺中市西區403華美西街一段142號6樓之1",
    "電話": "04-23144618",
    "傳真": "0952117956",
    "電子郵件": "jilwan.wang@msa.hinet.net",
    "會員人數": "117",
    "會員代表人數": "0",
    "宗旨": "發揚並保存中華傳統文化，提昇幽直生活且能永續為宗旨。",
    "任務": "發揚中國固有傳統文化，如藍染、陶藝、漆器、國化、書法、編織、傳統美食。\r\n協助單親家庭弱勢族群及外籍新娘學習多項專長及技能和語言的溝通。\r\n藝術品創作推廣及協助會員辦理作品展覽等等。",
    "全國性\/地區性": "全國性",
    "行政區": "臺中市"
}