{
    "團體類型": "社會團體",
    "團體分類": "醫療衛生團體",
    "團體名稱": "蘆葦營身心靈恢復協會",
    "現任理事長": "陳紹基",
    "理事長屆次": "1",
    "理事長任期": "104-10-17",
    "成立日期": "104-10-17",
    "核准立案字號": "1050001574",
    "團體狀態": "已立案",
    "郵遞區號": "982",
    "會址": "花蓮縣卓溪鄉卓清村17鄰卓樂65-1號",
    "電話": "03-8887324",
    "會員人數": "37",
    "會員代表人數": "0",
    "宗旨": "本會為依法設立、非以營利為目的之社會團體,以協助酒癮藥癮者走向身心靈康復為宗旨。精神標語為「壓傷的蘆葦祂不折斷,將殘的燈火祂不吹滅」。",
    "任務": "一、以明尼蘇達模式協助酒癮、藥癮成癮者邁向身、心、靈康復。\r\n附註:明尼蘇達模式是首建於醫學、再以心理學的背景結構介入、最後引導成癮者自發進入社區疾病支持系統,三者環環相扣的康復方法。\r\n二、針對成癮科學研究、提供對其他從事類似工作機構教育訓練。\r\n三、對成癮疾病之家庭,提供家庭復原的方案及協助。\r\n四、協建社區性成癮者康復支持團體。\r\n五、成立出版部門,以著作或翻譯先進之成癮康復相關文獻書籍。\r\n六、與其它成癮康復機構合作、交換成癮康復經驗。",
    "全國性\/地區性": "全國性",
    "行政區": "花蓮縣"
}