{
    "團體類型": "社會團體",
    "團體分類": "學術文化團體",
    "團體名稱": "台灣星靈神念學會",
    "現任理事長": "朱玫菁",
    "理事長屆次": "1",
    "理事長任期": "105-05-28",
    "成立日期": "105-05-28",
    "核准立案字號": "1050042884",
    "團體狀態": "已立案",
    "郵遞區號": "804",
    "會址": "高雄市鼓山區龍勝路28號12樓(該會於105.12.9函報本部異動備查)",
    "電話": "(02)82419139",
    "電子郵件": "twspiritstar@gmail.com",
    "宗旨": "以推動身心靈成長，美化人心為宗旨。",
    "任務": "一、\t研究、推廣傳統與現代的神念相關理論知識與練習技術。\r\n二、\t舉辦神念課程、講座、工作坊、讀書會。\r\n三、\t推動神念相關書籍、有聲書、期刊、雜誌等出版。\r\n四、\t推廣成立各地的神念練習團體。\r\n五、\t設計、發展並推廣神念應用課程與輔助工具。\r\n六、\t辦理神念師資之教育訓練及進修。",
    "全國性\/地區性": "全國性",
    "行政區": "高雄市"
}