{
    "團體類型": "社會團體",
    "團體分類": "學術文化團體",
    "團體名稱": "中華民國森優實驗教育學會",
    "現任理事長": "蔣小梅",
    "理事長屆次": "1",
    "理事長任期": "103-04-13",
    "成立日期": "103-04-13",
    "核准立案字號": "1030231622",
    "團體狀態": "已立案",
    "郵遞區號": "402",
    "會址": "臺中市南區南和一街16巷14號",
    "電話": "04-25354040",
    "會員人數": "30",
    "會員代表人數": "0",
    "宗旨": "一、有感於目前社會道德淪喪，禮義廉恥束之高閣。故成立本會重申知禮、知書、知作人的重要性。\r\n二、有感於台灣教育正在上演失落的下一代，本會重拾中華傳統文化的精髓，也就是儒家和道家思想。以人性為本位，以仁愛為中心，藉以建立安定的社會。而教育的意義，就在為下一代子孫進行良善的啟蒙，冀望他們能培養與上一代看待事情不同的切入點，進而引領出更美好的社會風氣。",
    "任務": "一、鼓勵以多元教育發展和弘揚中華傳統文化並進的實驗教育，激燙出另一種實驗教育的優勢。\r\n二、建立實驗教育研究成果之實踐場域。\r\n三、培訓具備「因材施教」教育能力的師資。\r\n四、開發實驗教育相關課程，及相關教材、教材、教具與教法。\r\n五、贊助實驗教育教材之研究與出版。",
    "全國性\/地區性": "全國性",
    "行政區": "臺中市"
}