{
    "團體類型": "社會團體",
    "團體分類": "社會服務及慈善團體",
    "團體名稱": "中華民國至慧關懷身心靈協會",
    "現任理事長": "蔡尚緯",
    "理事長屆次": "2",
    "理事長任期": "106-04-20",
    "成立日期": "103-01-15",
    "核准立案字號": "1030117111",
    "團體狀態": "已立案",
    "郵遞區號": "802",
    "會址": "高雄市苓雅區新光路38號38樓-3",
    "電話": "07-9559688",
    "傳真": "07-2691657",
    "電子郵件": "kh5213060@yahoo.com.tw",
    "會員人數": "30",
    "會員代表人數": "0",
    "宗旨": "以推廣正確的健康觀念，提升生活品質、關懷病痛、尊重生命，注重身心靈健康，並促進社會和諧為宗旨。",
    "任務": "一、舉辦身心靈健康研討會。\r\n二、配合社會福利政策，推展身心健康活動。\r\n三、協助政府推行政令。\r\n四、其他。",
    "全國性\/地區性": "全國性",
    "行政區": "高雄市"
}