{
    "團體類型": "社會團體",
    "團體分類": "經濟業務團體",
    "團體名稱": "中華經貿物流發展協會",
    "現任理事長": "趙伯良",
    "理事長屆次": "2",
    "理事長任期": "103-08-30",
    "成立日期": "99-10-02",
    "核准立案字號": "0990203581",
    "團體狀態": "已立案",
    "會址": "臺北市松江路206號7樓之8",
    "電話": "02-25432378、0932219164",
    "傳真": "02-25431728",
    "會員人數": "0",
    "會員代表人數": "0",
    "宗旨": "為配合國內、外經濟發展之需要。因應兩岸加強國際化、自由化之趨勢， 結合相關政商界、產業界、學術界及對本會宗旨認同之人士，以健全經貿物流企業經營體質，提昇經貿物流企業競爭力．建立經貿物流企業資源價值效率化、技術化、流通化、多元化的經營模式，進而落實物流企業策略聯盟之「管理理念」，建立經貿物流企業共同體及經貿物流企業區域經濟圈為目標。",
    "任務": "一、促進經貿物流企業經營之健全、擴大企業資源之基礎。\r\n二、推展落實經貿物流企業策略聯盟之理念。 \n三、建立經貿物流企業資源經營交流之管道。 \n四、研究發展經貿物流企業價值知識與技術，並發行相關圖書刊物資訊。 \n五、培育企業人員知識與技術創新，舉辦相關研討會成果觀摩發表會。 \n六、推行建立經貿物流企業共同體及區域經濟圈之理念。 \n七、研發經貿物流企業行銷技巧與市場策略管理制度。 \n八、研究提昇經貿物流企業資源之利用與分配，創造經貿物流企業資源高度化之發展。 \n九、提供經貿物流企業經營管理、供應鏈安全、財務規劃與管控、法務商務之資訊與諮詢服務。 \n十、促進兩岸及國際經貿物流企業經營管理、行銷技術及資源運用之交流。\r\n十一、接受委託辦理促進兩岸及國際商務活動之事項。\r\n十二、其他有關增進會員福利及會務推展事項。\r\n十三、其他有關增進會員福利及會務推展事項。\r\n十四、積極推廣產業及行業職能發展，培養個人終身學習，藉以提升就業能力。\r\n十五、協助政府宣導正確職業道德觀念，提昇就業技能及建立核心職能。\r\n十六、承辦政府機關與民間機構委託之就業促進業務。",
    "全國性\/地區性": "全國性",
    "行政區": "臺北市"
}