{
    "團體類型": "社會團體",
    "團體分類": "學術文化團體",
    "團體名稱": "中華易經養生證照推廣學會",
    "現任理事長": "吳美玉",
    "理事長屆次": "3",
    "理事長任期": "104-01-24",
    "成立日期": "95-08-12",
    "核准立案字號": "0950137731",
    "團體狀態": "已立案",
    "郵遞區號": "242",
    "會址": "新北市新莊區中原路127號4樓之3",
    "電話": "0928203399",
    "傳真": "02-89941114",
    "會員人數": "175",
    "會員代表人數": "0",
    "宗旨": "以推動易經研究，建立養生之理論，建立及推廣證照制度以提昇生活品質為宗旨。",
    "任務": "一、蒐集整理易經養生之相關資訊。\r\n二、推動易經養生之研究。\r\n三、建立易經養生之研究。\r\n四、推廣易經養生實踐。\r\n五、推動易經養生之檢定。\r\n六、建立易經養生證照制度並推廣。\r\n七、社會服務之參與。\r\n八、會員權益維護及聯誼。\r\n九、其他。",
    "全國性\/地區性": "全國性",
    "行政區": "新北市"
}