{
    "團體類型": "社會團體",
    "團體分類": "宗教團體",
    "團體名稱": "台灣成佛科學研究社",
    "現任理事長": "鍾志樑",
    "理事長屆次": "1",
    "理事長任期": "104-06-19",
    "成立日期": "104-01-25",
    "核准立案字號": "1040079884",
    "團體狀態": "已立案",
    "郵遞區號": "330",
    "會址": "桃園市桃園區復興路83號3樓之5",
    "電話": "03-3580764",
    "會員人數": "33",
    "會員代表人數": "0",
    "宗旨": "本社為依法設立、非以營利為目的之社會團體,宗旨有二,一是救地球:用成佛科學來導正現代科學之偏差,使它隨順佛法而不相背,以解除當前地球及人類的大危機。二是度眾生:教導人類如實學習成佛科學,真正理解佛法之義諦,隨順佛法,逐步修行, 漸次上進,以至成佛。",
    "任務": "一、成立成佛科學講堂,舉辦有益於社會的成佛科學講座,以淨化人心及心靈改革。\r\n二、出版科學佛法系列書籍,以推動佛陀教義之研究與闡揚。\r\n三、依法規申請推廣講經錄音帶、錄影帶、經書 光碟片等流通。\r\n四、提倡機關團體、學校、電視、電台之宣揚淨。\r\n五、配合政府推動各項慈善、淨化社會活動,落實導正社會風氣。\r\n六、其他一切有利於公益文化等相關事項之推展。",
    "全國性\/地區性": "全國性",
    "行政區": "桃園市"
}