{
    "團體類型": "社會團體",
    "團體分類": "體育運動團體",
    "團體名稱": "中華民國西班牙舞蹈協會",
    "現任理事長": "滕華君",
    "理事長屆次": "4",
    "理事長任期": "103-03-15",
    "成立日期": "90-12-05",
    "核准立案字號": "0910065512",
    "團體狀態": "已立案",
    "郵遞區號": "251",
    "會址": "新北市淡水區淡金路38巷7號21樓",
    "會員人數": "0",
    "會員代表人數": "0",
    "宗旨": "本會為依法設立、非以營利為目的之社會團體，以推廣西班牙舞蹈藝術為宗旨。",
    "任務": "一、推廣西班牙舞蹈藝術進入學校專業藝術教育、學校一般藝術教育及社會藝術教育體系。\r\n二、獎勵全球華人專業人士參與西班牙舞蹈學術研究，補助學校社團活動及優秀人才出國深造。\r\n三、辦理與西班牙舞蹈相關之課程、評鑑、比賽、展演及國際交流等活動。",
    "全國性\/地區性": "全國性",
    "行政區": "新北市"
}