{
    "團體類型": "社會團體",
    "團體分類": "經濟業務團體",
    "團體名稱": "中華職人產業文化推廣協會",
    "現任理事長": "吳昭儀",
    "理事長屆次": "3",
    "理事長任期": "105-02-20",
    "成立日期": "101-02-25",
    "核准立案字號": "1010136020",
    "團體狀態": "已立案",
    "郵遞區號": "407",
    "會址": "臺中市西屯區大隆路179號2樓",
    "電話": "04-23194688*1005、0988078660楊先生",
    "傳真": "04-23195088",
    "電子郵件": "iwork100@gmail.com",
    "會員人數": "0",
    "會員代表人數": "0",
    "宗旨": "以「提升個人專業知識及技術，推動產業文化活動，增進職人優勢，創造產業價值，促進產業經營之發展」為宗旨。",
    "任務": "一、舉辦教育訓練活動，提昇個人專業知識及技術。\r\n二、辦理產業文化活動，創造產業價值。\r\n三、推動產業證照認證，引領專業導航。\r\n四、搭設產業文化平台，促進產業交流。\r\n五、整合產業界需求，敦促相關單位改善經營環境。\r\n六、協助開發輔導及爭取相關就業之商機。\r\n七、舉辦其他與本會宗旨相關之活動。",
    "全國性\/地區性": "全國性",
    "行政區": "臺中市"
}