{
    "團體類型": "社會團體",
    "團體分類": "社會服務及慈善團體",
    "團體名稱": "台灣見松養生慈善協會",
    "現任理事長": "黃聖博",
    "理事長屆次": "1",
    "理事長任期": "104-02-25",
    "成立日期": "103-12-28",
    "核准立案字號": "1040037227",
    "團體狀態": "已立案",
    "郵遞區號": "804",
    "會址": "高雄市鼓山區華榮路89號14樓",
    "電話": "07-5522745",
    "會員人數": "50",
    "會員代表人數": "0",
    "宗旨": "推廣養生保健相關活動.促進全民身心健康.次要為資助孤兒及單親且學優的清寒學子等相關慈善活動",
    "任務": "1.廣泛結合國內外對養生保健活動相關團體學者推展養生保健活動\r\n2.出版養生保健會訊或雜誌或設立慈善養生保健網站普及養生保健觀念給廣大民眾\n3.義務服務社會協助整府推動各項公益活動餐與政府或民間團體進行養生自我保健推廣\n4.提供獎助學機資助孤兒及單親且學業優異清寒學生\n5.資助合於宗智及任務之研究主題德博碩士論文或研究\r\n6.本會之主管機關為內政部本會之目的事業應受各該事業主管機關之指導監督",
    "全國性\/地區性": "全國性",
    "行政區": "高雄市"
}