{
    "團體類型": "社會團體",
    "團體分類": "學術文化團體",
    "團體名稱": "台灣傳播管理研究協會",
    "現任理事長": "邱琪瑄",
    "理事長屆次": "3",
    "理事長任期": "103-04-02",
    "成立日期": "94-09-07",
    "核准立案字號": "0940037297",
    "團體狀態": "已立案",
    "郵遞區號": "111",
    "會址": "臺北市士林區中山北路5段250號銘傳大學傳播學院辦公室",
    "電話": "02-28824564-2467",
    "傳真": "02-28818675",
    "電子郵件": "kevinc@mcu.edu.tw",
    "會員人數": "58",
    "會員代表人數": "0",
    "宗旨": "以促進傳播產學之交流及提升傳播產業管理水準。",
    "任務": "一、舉辦傳播產學交流活動。\r\n二、從事傳播管理的研究。\r\n三、推動傳播管理知識的產業化。",
    "全國性\/地區性": "全國性",
    "行政區": "臺北市"
}