{
    "團體類型": "社會團體",
    "團體分類": "經濟業務團體",
    "團體名稱": "中華無店面商務發展協會",
    "現任理事長": "廖尚文",
    "理事長屆次": "3",
    "理事長任期": "102-01-30",
    "成立日期": "96-05-03",
    "核准立案字號": "096008302",
    "團體狀態": "解散",
    "解散日期": "105-06-30",
    "郵遞區號": "115",
    "會址": "臺北市南港區115園區街3-1號11樓之1",
    "電話": "02-66076037塗家興",
    "傳真": "02-2655-8336",
    "電子郵件": "lh9302@server.iii.org.tw",
    "會員人數": "182",
    "會員代表人數": "0",
    "宗旨": "本會以提昇台灣無店面零售業各類產業之技術與品質,促成跨業合作與整合,建立良好的消費環境,提供良好消費關係平台,引進國際新興經營觀念,推動全球化發展策略及佈局,以促進相關事業之發展與繁榮為宗旨",
    "任務": "一.協助建立產業定位:目前實體通路已有明確規範,本會成立後,將可協助虛擬通路產業的界定作更明確定位\r\n二.協助建立整合平台:協助整合國內網路購物、電視購物、型錄購物及行動購物等虛擬通路銷售平台,促成整合之綜效\r\n三.推動商業自動化及電子化:本會將致力協助虛擬通路之產業自動化及電子化",
    "全國性\/地區性": "全國性",
    "行政區": "臺北市"
}