{
    "團體類型": "社會團體",
    "團體分類": "社會服務及慈善團體",
    "團體名稱": "台灣超越巔峰關懷癲癇聯盟",
    "現任理事長": "曾幼玲",
    "理事長屆次": "1",
    "理事長任期": "102-07-27",
    "成立日期": "102-07-27",
    "核准立案字號": "1020279289",
    "團體狀態": "已立案",
    "郵遞區號": "231",
    "會址": "新北市新店區安成街45號2樓",
    "電子郵件": "alice@cosmiccare.org",
    "會員人數": "92",
    "會員代表人數": "0",
    "宗旨": "以維護、促進癲癇患者之權利與福利為宗旨。",
    "任務": "一、要求政府重視癲癇患者之權利與福利。修正癲癇身障鑑定之嚴苛內容。\r\n二、凝聚各地癲癇患者及家屬情誼。\r\n三、促進學校與社會對癲癇患者之瞭解與關懷。\r\n四、協助癲癇患者提升自信、激發潛能，勇敢走出生活陰霾。\r\n五、舉辦各項活動並聯誼其他社會團體，籍以增進癲癇患者人際關係。\r\n六、邀請癲癇醫療專家與學者參與癲癇衛教講座與座談會。\r\n七、傳達癲癇衛教與癲癇資訊。\r\n八、籲請設立癲癇患者職技訓練中心，訓練後輔導就業。\r\n九、促請政府及各醫療機構設立癲癇患者照護之家。\r\n十、懇請政府設立庇護工廠或庇護家園，安置癲癇患者。",
    "全國性\/地區性": "全國性",
    "行政區": "新北市"
}