{
    "團體類型": "社會團體",
    "團體分類": "宗親會",
    "團體名稱": "世界柯蔡宗親總會",
    "現任理事長": "蔡定邦",
    "理事長屆次": "19",
    "理事長任期": "105-11-27",
    "成立日期": "67-10-07",
    "核准立案字號": "819971",
    "團體狀態": "已立案",
    "郵遞區號": "104",
    "會址": "臺北市中山區吉林路109號5樓",
    "電話": "0937028809",
    "傳真": "02-25218789",
    "電子郵件": "kt109.world@msa.hinet.net",
    "會員人數": "1640",
    "會員代表人數": "62",
    "宗旨": "宗旨如下:遵循祖訓，敦親睦族，本互助互惠原則，團結世界各國各地宗親，互相聯誼，發揚倫理道德文化，服務社會人群，促進世界和平",
    "任務": "一、聯誼宗親，服務宗族\n二、發行世界柯蔡宗親雜誌\r\n三、辦理各國分會之交流事宜&hellip;等等",
    "全國性\/地區性": "全國性",
    "行政區": "臺北市"
}