{
    "團體類型": "社會團體",
    "團體分類": "經濟業務團體",
    "團體名稱": "中華民國電梯協會",
    "現任理事長": "許作名",
    "理事長屆次": "14",
    "理事長任期": "105-05-05",
    "成立日期": "71-04-18",
    "核准立案字號": "101827",
    "團體狀態": "已立案",
    "郵遞區號": "114",
    "會址": "臺北市內湖區港墘路221巷21號2樓",
    "傳真": "02-26573322",
    "電子郵件": "admi@elevator.org.tw",
    "會員人數": "2170",
    "會員代表人數": "0",
    "宗旨": "本會為協助政府推行國家建設與經濟發展工業安全政策，增進升降設備，機械停設備、機械遊樂設施效益、維護升降設備、機械停車設備及機械遊樂設施等安全，以發揚社會服務精神，達到民生樂利為宗旨",
    "任務": "一、接受委託有關升降設備、機械停車設備、機械遊樂設施等之各種安全檢驗及檢驗人員講習等技術服務事項\r\n二、接受委託有關升降設備、機械停車設備、機械遊樂設施等之技術服務事項",
    "全國性\/地區性": "全國性",
    "行政區": "臺北市"
}