{
    "團體類型": "社會團體",
    "團體分類": "同學校友會",
    "團體名稱": "中華民國中國醫藥大學校友會",
    "現任理事長": "陳惠明",
    "理事長屆次": "3",
    "理事長任期": "103-05-04",
    "成立日期": "95-04-23",
    "核准立案字號": "0950100242",
    "團體狀態": "已立案",
    "郵遞區號": "500",
    "會址": "彰化縣彰化市民生路37號",
    "電話": "04-7223646",
    "傳真": "04-7286675",
    "會員人數": "106",
    "會員代表人數": "0",
    "宗旨": "以聯繫校友感情，增進相互寮解與友誼，砥礪校友會學術研究，並提供或交換執業心得與最新醫藥科技知識，以互助合作謀求校友之更多發展，且將母校洪陽光大為宗旨。",
    "任務": "舉辦各項聯繫校友感情，增進相互寮解與友誼之活動。\r\n舉辦有關促進校友學術研究，相互提供或交換執業心得與最新醫藥科技之事之活動。\r\n舉辦有關促進校友互動合作，以謀求校友更多發展之活動。",
    "全國性\/地區性": "全國性",
    "行政區": "彰化縣"
}