{
    "團體類型": "社會團體",
    "團體分類": "同學校友會",
    "團體名稱": "中華民國陸軍專科學校校友總會",
    "現任理事長": "陳俊生",
    "理事長屆次": "3",
    "理事長任期": "104-12-20",
    "成立日期": "96-05-12",
    "核准立案字號": "0960162380",
    "團體狀態": "已立案",
    "郵遞區號": "106",
    "會址": "臺北市大安區復興南路1段342號12樓之5",
    "電話": "03-2205185",
    "傳真": "03-2288828",
    "會員人數": "56",
    "會員代表人數": "0",
    "宗旨": "發揮士校人之精神,團結互助倡導愛國情操,以文化、教育、藝術、體育、公益、慈善、傳統民俗技藝等活動端正社會善良風格,加強校友間連繫,增進情感達到融洽互助",
    "任務": "一.連繫校友(眷屬)、舉辦聯誼活動、促進情感\r\n二.發行會刊、報導校友動態、母校近況\r\n三.舉辦文化、教育、藝術、體育、公益、慈善、傳統民俗技藝等活動,提倡淨化心靈,達到真善美之境界",
    "全國性\/地區性": "全國性",
    "行政區": "臺北市"
}