{
    "團體類型": "社會團體",
    "團體分類": "經濟業務團體",
    "團體名稱": "中華企業經營管理服務協會",
    "現任理事長": "吳有田",
    "理事長屆次": "1",
    "理事長任期": "98-01-04",
    "成立日期": "98-01-04",
    "核准立案字號": "0980028642",
    "團體狀態": "已立案",
    "郵遞區號": "242",
    "會址": "新北市新莊區龍安路66號7樓",
    "電話": "02-2906-5231",
    "會員人數": "0",
    "會員代表人數": "0",
    "宗旨": "以結合企業、政府及學術界力量，協助企業經營管理，降低經營風\n　　　　　　險，建立企業形象，推廣公益活動，並提供法律、稅務及勞務等相關服務",
    "任務": "一、提供企業經營管理服務，降低企業經營風險。  \n二、辦理有關企業管理、法律、稅務及勞務等講座或教育訓練。\r\n三、協助企業有關勞務風險資料之分析與規劃。\r\n四、與相關企業或社團交流聯誼，以協助企業拓展商機合作事項。\r\n五、發行或提供有關企業經營之叢書、資訊。\r\n六、自籌或受政府委託，辦理有關企業經營管理之公益活動。\r\n七、辦理社會福利事業，推廣有關文教、志願及公益服務等工作。\r\n八、有關達成本會宗旨之其他事項。",
    "全國性\/地區性": "全國性",
    "行政區": "新北市"
}