{
    "團體類型": "社會團體",
    "團體分類": "經濟業務團體",
    "團體名稱": "中華商業聯合會",
    "現任理事長": "陳大業",
    "理事長屆次": "1",
    "理事長任期": "102-04-07",
    "成立日期": "102-04-07",
    "核准立案字號": "1020170478",
    "團體狀態": "已立案",
    "郵遞區號": "112",
    "會址": "臺北市北投區裕民六路128號6樓",
    "電話": "02-28282677",
    "會員人數": "30",
    "會員代表人數": "0",
    "宗旨": "本會為促進商業機會的正向發展以及推動台灣經濟環境成長，配合國家政策創造經濟價值的模式，運用有效的國際商業資訊，爭取國際間合作之商業活動及商業發展，讓產業及行業有更開拓的商業機會，來增進商業目標與社會公益的平衡，不僅豐富社會群體的生活，更期許社會向上發展。",
    "任務": "1. 提供擴展海外市場公司之策略諮商，解決架構障礙。\r\n2. 發行電子周報郵件提供最新有關華商經濟多元資訊。\r\n3. 發行中華商聯會刊 (季刊)，在每個領域內深入分析最新的商業趨勢。\r\n4. 舉行各種商業研討會和活動。\r\n5. 建立和許多國家地區的華商團體結盟，並提供會員相關商業貿易關係的服務。",
    "全國性\/地區性": "全國性",
    "行政區": "臺北市"
}