{
    "團體類型": "社會團體",
    "團體分類": "經濟業務團體",
    "團體名稱": "中華法政工商暨農漁環保教育協會",
    "現任理事長": "蕭肇陽",
    "理事長屆次": "2",
    "理事長任期": "103-05-10",
    "成立日期": "99-05-11",
    "核准立案字號": "0990105261",
    "團體狀態": "已立案",
    "會址": "嘉義市民權路116之1號7樓",
    "電話": "05-2714380",
    "傳真": "05-2753572",
    "電子郵件": "fortune88168@gmail.com",
    "會員人數": "0",
    "會員代表人數": "0",
    "宗旨": "配合政府的政令及政策，提升並發展我國崇法尊律的民主政治與優質的勞工及工商業；並加強推廣環保意識，研發及提升我國精緻的農漁業和教育事業之競爭力；進而營造全民健康的優質永續經營及安身立命的生活環境。",
    "任務": "關於我國法律、政治、工商、農漁業、環保及教育等之倡導推動及技術服務等事項。\r\n關於我國法律、政治、工商、農漁業、環保及教育等之講座、研討、研發及推廣等活動。\r\n有關關懷弱勢團體活動的經費贊助及舉辦等等。",
    "全國性\/地區性": "全國性",
    "行政區": "嘉義市"
}