{
    "團體類型": "社會團體",
    "團體分類": "社會服務及慈善團體",
    "團體名稱": "中華國際婚姻保護協會",
    "現任理事長": "洪子賢",
    "理事長屆次": "1",
    "理事長任期": "94-04-30",
    "成立日期": "94-04-30",
    "核准立案字號": "0940019116",
    "團體狀態": "已立案",
    "郵遞區號": "242",
    "會址": "新北市新莊區中正路343號5樓",
    "會員人數": "0",
    "會員代表人數": "0",
    "宗旨": "提供學習、生活扶助、婚前講習、婚姻協談諮商、文書處理等方面之具體協助來提昇國際婚姻家庭適應能力，真正保護國際婚姻配偶平等平和融入社會之權益，繼而保護國際婚姻家庭和諧穩固。",
    "任務": "一、協助政府推行族群融和相關政策政令。\r\n二、辦理國際婚姻新人參加婚前講習（依家庭教育法）時向政府機關申請及轉介予主辦講習單位之相關聯繫服務事項。\r\n三、辦理國際婚姻配偶語言、文化、風俗習慣、社會制度等相關適應研習。",
    "全國性\/地區性": "全國性",
    "行政區": "新北市"
}