{
    "團體類型": "社會團體",
    "團體分類": "醫療衛生團體",
    "團體名稱": "臺灣健康醫院學會",
    "現任理事長": "黃暉庭",
    "理事長屆次": "3",
    "理事長任期": "104-11-21",
    "成立日期": "96-08-19",
    "核准立案字號": "0960146624",
    "團體狀態": "已立案",
    "郵遞區號": "105",
    "會址": "臺北市松山區八德路二段346巷5號2樓",
    "電話": "02-27528394",
    "傳真": "02-27521334",
    "會員人數": "85",
    "會員代表人數": "0",
    "宗旨": "本會為依法設立、非以營利為目的之社會團體，以提昇醫療院所健康促進之文化與效能，推廣相關學術研究及教育，加強國際交流，以增進病人、醫療院所人員、家屬與社區之健康為宗旨。",
    "任務": "一、醫療院所健康促進文化之提倡、推廣與研究；二、醫療院所健康促進環境、流程與管理之改善、研發與推廣；三、醫療院所健康促進學理、標準、工具與方法等之研發與推廣； 四、國際健康促進醫療院所網絡之國內推廣、會員招募、資格審查 暨國際合作交流等事項；五、醫療院所健康促進師資與人力之拓展與培育事項；六、增進政府、衛生醫療界與社會對醫療院所健康促進之重視與支持；七、其他有關醫療院所健康促進之事項。",
    "全國性\/地區性": "全國性",
    "行政區": "臺北市"
}