{
    "團體類型": "社會團體",
    "團體分類": "經濟業務團體",
    "團體名稱": "台灣網際網路協會",
    "現任理事長": "李彬",
    "理事長屆次": "6",
    "理事長任期": "105-06-15",
    "成立日期": "88-11-05",
    "核准立案字號": "8840322",
    "團體狀態": "已立案",
    "郵遞區號": "100",
    "會址": "臺北市中正區信義路1段21號數據通信大樓1401室",
    "電話": "02-66380818",
    "傳真": "02-66368668",
    "電子郵件": "twia@taiwanmobile.com",
    "會員人數": "0",
    "會員代表人數": "0",
    "宗旨": "為增進會員專業知識、發展推廣國內外網路事業，促記我國國際網路技術與應用，推動網路文化教育，協調同業關係，增進共同利益及舉辦對網際網路發展有益之各項活動為宗旨。",
    "任務": "關於國內外網際網路相關業務之統計及研究、發展事項。\r\n關於國內外網路事業之聯繫、介紹及推廣事項。\r\n配合政府訂定會員之善良自律規範，以建立良好之公益形象等等。",
    "全國性\/地區性": "全國性",
    "行政區": "臺北市"
}